{
  "year": "106",
  "subject_slug": "science",
  "subject_label": "自然",
  "question_count": 54,
  "answered_count": 54,
  "page_count": 14,
  "ocr_pages": [],
  "files": {
    "pdf": "cap_practice_sources\\106\\science\\106_science.pdf",
    "docx": "cap_practice_word\\106\\106_science.docx"
  },
  "official": {
    "question_url": "https://drive.google.com/file/d/1nKOX2Y_Lc97oRP0CNdibx3sdWo4zWj2s/view?usp=drive_link",
    "answer_url": "https://drive.google.com/file/d/1SDrO_xG9MG6Kmcg1H9ibY_NM410de9VF/view?usp=drive_link",
    "explanation_url": "https://drive.google.com/file/d/16HOh22LGO2laMdfIZSpXIQG-lfADP7LB/view?usp=drive_link"
  },
  "checks": {
    "question_chunks_found": 58,
    "answers_found": 54,
    "questions_kept": 54,
    "issues_found": 4,
    "answer_completion_ratio": 1.0
  },
  "practice_ready": true,
  "questions": [
    {
      "number": 1,
      "display_number": 1,
      "page_number": 2,
      "context": "",
      "stem": "圖(一)為地面天氣簡圖，圖中經過臺灣的線條，其所代 表的數值與單位為下列何者？",
      "options": {
        "A": "1004 百帕(hPa)",
        "B": "1008 百帕(hPa)",
        "C": "1004 公分水銀柱(cm-Hg)",
        "D": "1008 公分水銀柱(cm-Hg)"
      },
      "correct_answer": "B",
      "explanation": "這題的正確答案是 B。 對應選項內容是「1008 百帕(hPa)」。 先抓題幹關鍵詞，再用刪去法排除不符合條件的選項。 這題來自 106 年會考自然科，建議先回頭確認關鍵概念與題目限制。"
    },
    {
      "number": 2,
      "display_number": 2,
      "page_number": 2,
      "context": "",
      "stem": "表(一)為生活在南極的動物及其食物來源，根據此表判斷，下列有關這些動物 之間交互關係的敘述，何者最合理？",
      "options": {
        "A": "虎鯨和藍鯨為捕食關係",
        "B": "虎鯨和藍鯨為競爭關係",
        "C": "帝王企鵝和阿德列企鵝為捕食關係",
        "D": "帝王企鵝和阿德列企鵝為競爭關係"
      },
      "correct_answer": "A",
      "explanation": "這題的正確答案是 A。 對應選項內容是「虎鯨和藍鯨為捕食關係」。 先抓題幹關鍵詞，再用刪去法排除不符合條件的選項。 這題來自 106 年會考自然科，建議先回頭確認關鍵概念與題目限制。"
    },
    {
      "number": 3,
      "display_number": 3,
      "page_number": 2,
      "context": "",
      "stem": "已知一地區的某種蝸牛其外殼有深色及淺色之分。在此地區無論是陰暗的石 頭縫處或明亮的草地處皆可發現此種蝸牛，且此地區有一種以此蝸牛為食的 天敵。阿泰調查了此種蝸牛在兩處的數量後作圖，並據此推論出該天敵主要 是利用視覺捕食蝸牛，下列何者最可能是他的調查結果？",
      "options": {
        "A": "",
        "B": "",
        "C": "",
        "D": ""
      },
      "correct_answer": "B",
      "explanation": "這題的正確答案是 B。 先抓題幹關鍵詞，再用刪去法排除不符合條件的選項。 這題來自 106 年會考自然科，建議先回頭確認關鍵概念與題目限制。"
    },
    {
      "number": 4,
      "display_number": 4,
      "page_number": 2,
      "context": "",
      "stem": "圖(二)為對兩塊銅塊分別進行甲和乙兩種操作的示意圖，關於這兩種操作造成 外觀上的改變是否為化學變化，下列判斷何者正確？",
      "options": {
        "A": "兩種都是",
        "B": "兩種都不是",
        "C": "只有甲操作是",
        "D": "只有乙操作是\n圖(一)\n圖(二)\n\u001b\n\u001a\u0019\n\u0018\u0017\n\u0016\u0017、\u0014\u0013\n\u0016\u0017\n\u0012\u0011\n\u0010\u000f\u000e\n、\n\b\u0007\u0006\u000e\n\u0012\u0011\n表(一)\n抽拉成細絲\n(形狀改變)\n加熱至銅表面氧化\n成黑色(顏色改變)"
      },
      "correct_answer": "D",
      "explanation": "這題的正確答案是 D。 對應選項內容是「只有乙操作是\n圖(一)\n圖(二)\n\u001b\n\u001a\u0019\n\u0018\u0017\n\u0016\u0017、\u0014\u0013\n\u0016\u0017\n\u0012\u0011\n\u0010\u000f\u000e\n、\n\b\u0007\u0006\u000e\n\u0012\u0011\n表(一)\n抽拉成細絲\n(形狀改變)\n加熱至銅表面氧化\n成黑色(顏色改變)」。 先抓題幹關鍵詞，再用刪去法排除不符合條件的選項。 這題來自 106 年會考自然科，建議先回頭確認關鍵概念與題目限制。"
    },
    {
      "number": 5,
      "display_number": 5,
      "page_number": 3,
      "context": "",
      "stem": "爸爸帶著兒子與女兒到公園玩蹺蹺板，三人所坐的位置如圖(三)所示，爸爸、兒 子、女兒的體重分別為 75 kgw、20 kgw、25 kgw。此時「爸爸的體重使蹺蹺板產 生的力矩大小」大於「兒子與女兒的體重使蹺蹺板產生的力矩大小和」，蹺蹺板 將倒向爸爸那一端，若他們希望減少兩邊力矩的差距，則下列調整位置的方式， 哪一個可能達到他們的目的？",
      "options": {
        "A": "爸爸換到位置甲",
        "B": "兒子換到位置乙",
        "C": "女兒換到位置乙",
        "D": "兒子、女兒的位置互換"
      },
      "correct_answer": "B",
      "explanation": "這題的正確答案是 B。 對應選項內容是「兒子換到位置乙」。 先抓題幹關鍵詞，再用刪去法排除不符合條件的選項。 這題來自 106 年會考自然科，建議先回頭確認關鍵概念與題目限制。"
    },
    {
      "number": 6,
      "display_number": 6,
      "page_number": 3,
      "context": "",
      "stem": "圖(四)為某實驗器材的三種使用方法，哪幾種使用方法不恰當？",
      "options": {
        "A": "方法甲和方法乙",
        "B": "方法甲和方法丙",
        "C": "方法乙和方法丙",
        "D": "三種方法都不恰當"
      },
      "correct_answer": "A",
      "explanation": "這題的正確答案是 A。 對應選項內容是「方法甲和方法乙」。 先抓題幹關鍵詞，再用刪去法排除不符合條件的選項。 這題來自 106 年會考自然科，建議先回頭確認關鍵概念與題目限制。"
    },
    {
      "number": 7,
      "display_number": 7,
      "page_number": 3,
      "context": "",
      "stem": "圖(五)為去汙作用的步驟示意圖，下列哪一個反應可以產生與圖中物質甲相同 功能的產物？",
      "options": {
        "A": "乙醇 + 乙酸 →",
        "B": "碳酸鈣 + 鹽酸 →",
        "C": "油脂 + 氫氧化鈉 →",
        "D": "硫酸 + 氫氧化鈉 →"
      },
      "correct_answer": "C",
      "explanation": "這題的正確答案是 C。 對應選項內容是「油脂 + 氫氧化鈉 →」。 先抓題幹關鍵詞，再用刪去法排除不符合條件的選項。 這題來自 106 年會考自然科，建議先回頭確認關鍵概念與題目限制。"
    },
    {
      "number": 8,
      "display_number": 8,
      "page_number": 3,
      "context": "",
      "stem": "以導線連接五個燈座與一個電池，形成一個電 路，然後將甲、乙、丙、丁、戊五個燈泡裝入燈 座，如圖(六)所示。今圖中燈泡甲因燒毀而發生斷 路，導致其他燈泡都不亮。已知將燈泡甲跟某一 燈泡更換安裝位置後，未燒毀的四個燈泡均可再 次發亮，則燈泡甲應與下列哪一燈泡互換位置？",
      "options": {
        "A": "乙",
        "B": "丙",
        "C": "丁",
        "D": "戊\n圖(三)\n50mL\n50mL\n50mL\n50mL\n\u001b\n\u001a\u0019\n\u0018\u001b\n\u0017\u0016\u0015\u0014\u0013\u0019\n\u0012\u0014\n\u0011\u0010\n\u0017\u0016\n\u0013\n\u0017\u0016\n\u0014\u0013\n\u001b\n圖(四)\n圖(五)\n圖(六)\nΌ\n來回均勻加熱溶液\n加入後攪拌配成溶液\n測量不溶於水物質的體積"
      },
      "correct_answer": "B",
      "explanation": "這題的正確答案是 B。 對應選項內容是「丙」。 先抓題幹關鍵詞，再用刪去法排除不符合條件的選項。 這題來自 106 年會考自然科，建議先回頭確認關鍵概念與題目限制。"
    },
    {
      "number": 9,
      "display_number": 9,
      "page_number": 4,
      "context": "",
      "stem": "已知某種動物在同一個體中可產生卵及精子，但在繁殖時，仍需要與不同個 體交換精子後，才能受精並產生子代。下列關於此種動物生殖及子代的相關 敘述，何者最合理？",
      "options": {
        "A": "生殖方式屬於無性生殖",
        "B": "子代不具有生殖的能力",
        "C": "子代具有親代的部分特徵",
        "D": "子代行減數分裂增加體細胞"
      },
      "correct_answer": "C",
      "explanation": "這題的正確答案是 C。 對應選項內容是「子代具有親代的部分特徵」。 先抓題幹關鍵詞，再用刪去法排除不符合條件的選項。 這題來自 106 年會考自然科，建議先回頭確認關鍵概念與題目限制。"
    },
    {
      "number": 10,
      "display_number": 10,
      "page_number": 4,
      "context": "",
      "stem": "已知某植物的種子顏色是由一對等位 基因所控制，黃色為顯性，綠色為隱 性。小霖記錄了四組親代的表現型並 預測其子代可能出現的表現型，整理 成表(二)。在不考慮突變的情況下，表 中哪一組子代的預測最不合理？",
      "options": {
        "A": "甲",
        "B": "乙",
        "C": "丙",
        "D": "丁"
      },
      "correct_answer": "B",
      "explanation": "這題的正確答案是 B。 對應選項內容是「乙」。 先抓題幹關鍵詞，再用刪去法排除不符合條件的選項。 這題來自 106 年會考自然科，建議先回頭確認關鍵概念與題目限制。"
    },
    {
      "number": 11,
      "display_number": 11,
      "page_number": 4,
      "context": "",
      "stem": "三葉蟲有許多不同的種類，圖(七)為甲、乙、丙、丁四種三葉蟲的生存年代，圖 中黑色長條代表該三葉蟲生存的地質年代範圍。若有某地層是在寒武紀時沉 積形成，且含有三葉蟲化石，則下列對此地層的推論何者最合理？",
      "options": {
        "A": "只會有甲種的三葉蟲化石",
        "B": "只會有乙種的三葉蟲化石",
        "C": "不會有丙種的三葉蟲化石",
        "D": "不會有丁種的三葉蟲化石"
      },
      "correct_answer": "C",
      "explanation": "這題的正確答案是 C。 對應選項內容是「不會有丙種的三葉蟲化石」。 先抓題幹關鍵詞，再用刪去法排除不符合條件的選項。 這題來自 106 年會考自然科，建議先回頭確認關鍵概念與題目限制。"
    },
    {
      "number": 12,
      "display_number": 12,
      "page_number": 4,
      "context": "",
      "stem": "某雙子葉木本植物的莖具有樹皮及木材等構造，如 圖(八)所示。下列何者為圖中標示 處的主要功能？",
      "options": {
        "A": "運輸養分",
        "B": "運輸水分",
        "C": "細胞分裂",
        "D": "光合作用"
      },
      "correct_answer": "B",
      "explanation": "這題的正確答案是 B。 對應選項內容是「運輸水分」。 先抓題幹關鍵詞，再用刪去法排除不符合條件的選項。 這題來自 106 年會考自然科，建議先回頭確認關鍵概念與題目限制。"
    },
    {
      "number": 13,
      "display_number": 13,
      "page_number": 4,
      "context": "",
      "stem": "阿凱於某地收集雨水，並在 25℃的環境下以不同的試紙測試雨水的酸鹼性， 下列哪一種試紙的顏色變化情形，最可能是說明「此地雨水的pH值小於5.0」 的理由之一？",
      "options": {
        "A": "藍色石蕊試紙變成紅色",
        "B": "紅色石蕊試紙變成藍色",
        "C": "藍色氯化亞鈷試紙變成粉紅色",
        "D": "粉紅色氯化亞鈷試紙變成藍色\n\u001b\n\u001a\u0019\n\u0018\u0017\n\u0016\n\u0015\n\u0014\n\u0013\n\u0012\n\u0011\n\u0010\n\u000f\n\u000e\n圖(八)\n圖(七)\n表(二)\n紀為代之下更細分的年代單位"
      },
      "correct_answer": "A",
      "explanation": "這題的正確答案是 A。 對應選項內容是「藍色石蕊試紙變成紅色」。 先抓題幹關鍵詞，再用刪去法排除不符合條件的選項。 這題來自 106 年會考自然科，建議先回頭確認關鍵概念與題目限制。"
    },
    {
      "number": 14,
      "display_number": 14,
      "page_number": 5,
      "context": "",
      "stem": "圖(九)為阿謙進行實驗的步驟圖： 假設實驗過程中，硫粉燃燒後產生的氣體沒有散失，則步驟四完成後，分別取 其中一瓶溶液與其中一份大理石反應，反應初期何種組合其冒泡的速率最快？",
      "options": {
        "A": "甲瓶溶液和丙",
        "B": "甲瓶溶液和丁",
        "C": "乙瓶溶液和丙",
        "D": "乙瓶溶液和丁"
      },
      "correct_answer": "B",
      "explanation": "這題的正確答案是 B。 對應選項內容是「甲瓶溶液和丁」。 先抓題幹關鍵詞，再用刪去法排除不符合條件的選項。 這題來自 106 年會考自然科，建議先回頭確認關鍵概念與題目限制。"
    },
    {
      "number": 15,
      "display_number": 15,
      "page_number": 5,
      "context": "",
      "stem": "表(三)為四種物質在一大氣壓下的熔點及沸點。在 一大氣壓下，下列何者的溫度最高？",
      "options": {
        "A": "液態的鐵",
        "B": "液態的氮",
        "C": "固態的水",
        "D": "固態的鋁"
      },
      "correct_answer": "A",
      "explanation": "這題的正確答案是 A。 對應選項內容是「液態的鐵」。 先抓題幹關鍵詞，再用刪去法排除不符合條件的選項。 這題來自 106 年會考自然科，建議先回頭確認關鍵概念與題目限制。"
    },
    {
      "number": 16,
      "display_number": 16,
      "page_number": 5,
      "context": "",
      "stem": "一河川在甲、乙兩地設有碼頭，位置如圖(十)所示，圖(十一)是某日甲地受潮汐 影響的水位高度與時間關係圖。乙地的水位高度與時間關係變化趨勢與甲地相 同，但乙地的潮汐時間較甲地晚30分鐘，且受限於河床地形，船隻僅能在一天 中水位較高的連續四小時內，安全進出乙地的碼頭。推測下列何者最可能是該 日可安全進出乙地碼頭的時間範圍？",
      "options": {
        "A": "08:40～12:40",
        "B": "11:10～15:10",
        "C": "17:20～21:20",
        "D": "18:50～22:50"
      },
      "correct_answer": "B",
      "explanation": "這題的正確答案是 B。 對應選項內容是「11:10～15:10」。 先抓題幹關鍵詞，再用刪去法排除不符合條件的選項。 這題來自 106 年會考自然科，建議先回頭確認關鍵概念與題目限制。"
    },
    {
      "number": 17,
      "display_number": 17,
      "page_number": 5,
      "context": "",
      "stem": "下列何者與地球間的直線距離最遠？",
      "options": {
        "A": "太陽",
        "B": "海王星",
        "C": "哈雷彗星",
        "D": "銀河系中心\n圖(九)\n圖(十)\n:\n:\n(°C)\n(°C)\n表(三)\n圖(十一)\n點燃兩組\n質量相等的\n硫粉\n把燃燒中的硫粉\n分別置於甲、乙含\n有水的瓶內，直到\n完全燃燒\n完全燃燒後，蓋\n住瓶口，並搖晃\n廣口瓶使產物全\n都溶於水中\n再準備兩份質量\n相同，但外觀粗細\n不同的大理石"
      },
      "correct_answer": "D",
      "explanation": "這題的正確答案是 D。 對應選項內容是「銀河系中心\n圖(九)\n圖(十)\n:\n:\n(°C)\n(°C)\n表(三)\n圖(十一)\n點燃兩組\n質量相等的\n硫粉\n把燃燒中的硫粉\n分別置於甲、乙含\n有水的瓶內，直到\n完全燃燒\n完全燃燒後，蓋\n住瓶口，並搖晃\n廣口瓶使產物全\n都溶於水中\n再準備兩份質量\n相同，但外觀粗細\n不同的大理石」。 先抓題幹關鍵詞，再用刪去法排除不符合條件的選項。 這題來自 106 年會考自然科，建議先回頭確認關鍵概念與題目限制。"
    },
    {
      "number": 18,
      "display_number": 18,
      "page_number": 6,
      "context": "",
      "stem": "表(四)為甲細胞和乙細胞內有無兩種特定生理作用的比較。根據此表推測甲、 乙細胞內特定構造的有無，下列敘述何者最合理？",
      "options": {
        "A": "僅甲細胞含有粒線體",
        "B": "僅甲細胞含有葉綠體",
        "C": "僅乙細胞含有粒線體",
        "D": "僅乙細胞含有葉綠體"
      },
      "correct_answer": "D",
      "explanation": "這題的正確答案是 D。 對應選項內容是「僅乙細胞含有葉綠體」。 先抓題幹關鍵詞，再用刪去法排除不符合條件的選項。 這題來自 106 年會考自然科，建議先回頭確認關鍵概念與題目限制。"
    },
    {
      "number": 19,
      "display_number": 19,
      "page_number": 6,
      "context": "",
      "stem": "雅婷和怡君分別對牛頓第一運動定律提出自己的見解，其敘述如下： 雅婷：若靜止的物體不受外力作用，則此物體會一直維持靜止。 怡君：若運動中的物體所受合力為零，則此物體會一直作等速度運動。 關於兩人的敘述下列何者正確？",
      "options": {
        "A": "兩人均合理",
        "B": "兩人均不合理",
        "C": "只有雅婷合理",
        "D": "只有怡君合理"
      },
      "correct_answer": "A",
      "explanation": "這題的正確答案是 A。 對應選項內容是「兩人均合理」。 先抓題幹關鍵詞，再用刪去法排除不符合條件的選項。 這題來自 106 年會考自然科，建議先回頭確認關鍵概念與題目限制。"
    },
    {
      "number": 20,
      "display_number": 20,
      "page_number": 6,
      "context": "",
      "stem": "小安進行電解水的反應，其實驗如圖(十二)所示，在正極 產生8公克的氣體X。若氣體X全部由電解水的反應產生， 則消耗的水為多少莫耳？(氫、氧的原子量分別為1、16)",
      "options": {
        "A": "0.25",
        "B": "0.5",
        "C": "1",
        "D": "4"
      },
      "correct_answer": "B",
      "explanation": "這題的正確答案是 B。 對應選項內容是「0.5」。 先抓題幹關鍵詞，再用刪去法排除不符合條件的選項。 這題來自 106 年會考自然科，建議先回頭確認關鍵概念與題目限制。"
    },
    {
      "number": 21,
      "display_number": 21,
      "page_number": 6,
      "context": "",
      "stem": "如圖(十三)所示，在白光的照射下，阿舍所看見 圖卡中藍色、紅色、綠色、白色部分的面積分 別為8 cm2、4 cm2、2 cm2、2 cm2。用下列哪一 種顏色的光照射圖卡，阿舍最可能看見黑色部 分的面積為10 cm2？",
      "options": {
        "A": "紅光",
        "B": "藍光",
        "C": "綠光",
        "D": "白光"
      },
      "correct_answer": "A",
      "explanation": "這題的正確答案是 A。 對應選項內容是「紅光」。 先抓題幹關鍵詞，再用刪去法排除不符合條件的選項。 這題來自 106 年會考自然科，建議先回頭確認關鍵概念與題目限制。"
    },
    {
      "number": 22,
      "display_number": 22,
      "page_number": 6,
      "context": "",
      "stem": "製造硫酸的過程如下： 階段一：硫與氧氣燃燒產生二氧化硫 階段二：利用催化劑使二氧化硫與氧氣反應產生三氧化硫 再經由後續反應生成硫酸。上述兩階段反應中的還原劑分別為下列何者？",
      "options": {
        "A": "階段一為O2，階段二為O2",
        "B": "階段一為S，階段二為SO2",
        "C": "階段一為SO2，階段二為O2",
        "D": "階段一為SO2，階段二為SO2\n圖(十二)\n\u001b\n+\n表(四)\n圖(十三)"
      },
      "correct_answer": "B",
      "explanation": "這題的正確答案是 B。 對應選項內容是「階段一為S，階段二為SO2」。 先抓題幹關鍵詞，再用刪去法排除不符合條件的選項。 這題來自 106 年會考自然科，建議先回頭確認關鍵概念與題目限制。"
    },
    {
      "number": 23,
      "display_number": 23,
      "page_number": 7,
      "context": "",
      "stem": "阿強不幸漂流到了無人島，他在觀察潮汐一段時間之後，發現每個月有兩天滿潮 的水位最高。這兩天的月相，可能是滿月或是整天都看不到月亮，且為乘坐木筏 離開的最好時機，因此他在某個滿月的日子開始製作木筏。若阿強用了7天做好 木筏，只要等到有上述滿潮水位最高的日子就能離開，則他最快要再等大約多 久才可離開？",
      "options": {
        "A": "完工當天",
        "B": "7天",
        "C": "15天",
        "D": "21天"
      },
      "correct_answer": "B",
      "explanation": "這題的正確答案是 B。 對應選項內容是「7天」。 先抓題幹關鍵詞，再用刪去法排除不符合條件的選項。 這題來自 106 年會考自然科，建議先回頭確認關鍵概念與題目限制。"
    },
    {
      "number": 24,
      "display_number": 24,
      "page_number": 7,
      "context": "",
      "stem": "一般人手指觸電後會立刻縮手，也會感覺疼痛而 趕緊甩手。圖(十四)為人體指尖觸電時神經訊息傳 導的示意圖，圖中甲、乙、丙分別為訊息傳導所 經過的神經，下列有關此訊息傳導路徑相關敘述 與所對應的神經之配對，何者最合理？",
      "options": {
        "A": "觸電後立刻縮手—甲、乙",
        "B": "觸電後感覺疼痛—乙、丙",
        "C": "受器接受刺激後傳至中樞神經—乙、丙",
        "D": "中樞神經發出甩手的命令後傳至動器—丙、甲"
      },
      "correct_answer": "A",
      "explanation": "這題的正確答案是 A。 對應選項內容是「觸電後立刻縮手—甲、乙」。 先抓題幹關鍵詞，再用刪去法排除不符合條件的選項。 這題來自 106 年會考自然科，建議先回頭確認關鍵概念與題目限制。"
    },
    {
      "number": 25,
      "display_number": 25,
      "page_number": 7,
      "context": "",
      "stem": "表(五)是地球上甲、乙、丙三個地點的緯度，下列有關三地對流層內氣壓隨 垂直高度的變化趨勢比較，何者正確？",
      "options": {
        "A": "僅丙的變化趨勢隨高度增加而遞減",
        "B": "僅甲、乙的變化趨勢隨高度增加而遞減",
        "C": "三地的變化趨勢皆隨著高度增加而遞減",
        "D": "三地的變化趨勢皆隨著高度增加而增加"
      },
      "correct_answer": "C",
      "explanation": "這題的正確答案是 C。 對應選項內容是「三地的變化趨勢皆隨著高度增加而遞減」。 先抓題幹關鍵詞，再用刪去法排除不符合條件的選項。 這題來自 106 年會考自然科，建議先回頭確認關鍵概念與題目限制。"
    },
    {
      "number": 26,
      "display_number": 26,
      "page_number": 7,
      "context": "",
      "stem": "將臺灣在夏季時主要盛行的季風稱為甲，冬季時主要盛行的季風稱為乙，下 列有關甲、乙兩者的敘述，何者最合理？",
      "options": {
        "A": "兩者常會因經過海面而挾帶水氣",
        "B": "甲應為東南季風，乙應為西北季風",
        "C": "甲主要源自於高氣壓，乙主要源自於低氣壓",
        "D": "臺灣西南部因位處甲、乙的迎風面，而常有明顯降雨"
      },
      "correct_answer": "A",
      "explanation": "這題的正確答案是 A。 對應選項內容是「兩者常會因經過海面而挾帶水氣」。 先抓題幹關鍵詞，再用刪去法排除不符合條件的選項。 這題來自 106 年會考自然科，建議先回頭確認關鍵概念與題目限制。"
    },
    {
      "number": 27,
      "display_number": 27,
      "page_number": 7,
      "context": "",
      "stem": "圖(十五)為人體部分消化器官的示意圖，若老王體內 的甲處發生阻塞，則下列關於他的消化及養分吸收功 能，何者最可能發生？",
      "options": {
        "A": "胰液無法排至小腸內",
        "B": "胃液無法分解蛋白質",
        "C": "消化脂質的功能下降",
        "D": "吸收葡萄糖的功能下降\n圖(十四)\n圖(十五)\n表(五)"
      },
      "correct_answer": "C",
      "explanation": "這題的正確答案是 C。 對應選項內容是「消化脂質的功能下降」。 先抓題幹關鍵詞，再用刪去法排除不符合條件的選項。 這題來自 106 年會考自然科，建議先回頭確認關鍵概念與題目限制。"
    },
    {
      "number": 28,
      "display_number": 28,
      "page_number": 8,
      "context": "",
      "stem": "在無摩擦力的水平桌面上推動木塊，記錄下甲、乙、丙三組實驗中木塊的 質量(kg)、推動木塊的水平外力大小(N)、木塊的加速度大小(m/s 2)於表(六)， 根據表中數值，推測下列選項中X、Y、Z所代表的物理量，哪一個合理？",
      "options": {
        "A": "X：水平外力大小，Y：質量，Z：加速度大小",
        "B": "X：水平外力大小，Y：加速度大小，Z：質量",
        "C": "X：質量，Y：加速度大小，Z：水平外力大小",
        "D": "X：質量，Y：水平外力大小，Z：加速度大小"
      },
      "correct_answer": "D",
      "explanation": "這題的正確答案是 D。 對應選項內容是「X：質量，Y：水平外力大小，Z：加速度大小」。 先抓題幹關鍵詞，再用刪去法排除不符合條件的選項。 這題來自 106 年會考自然科，建議先回頭確認關鍵概念與題目限制。"
    },
    {
      "number": 29,
      "display_number": 29,
      "page_number": 8,
      "context": "",
      "stem": "已知化合物X在水中是一種強電解質。分析人員 偵測只含化合物X的甲、乙、丙和丁四杯不同濃 度的水溶液，並將化合物X解離出的正、負離子 數目作圖，如圖(十六)所示。由圖判斷下列何者 最可能是化合物X？",
      "options": {
        "A": "CaCl2",
        "B": "CuSO4",
        "C": "Na2SO4",
        "D": "CH3COOH"
      },
      "correct_answer": "C",
      "explanation": "這題的正確答案是 C。 對應選項內容是「Na2SO4」。 先抓題幹關鍵詞，再用刪去法排除不符合條件的選項。 這題來自 106 年會考自然科，建議先回頭確認關鍵概念與題目限制。"
    },
    {
      "number": 30,
      "display_number": 30,
      "page_number": 8,
      "context": "",
      "stem": "在一大氣壓下，甲、乙、丙三鋁塊質量分別為M 甲、 M 乙、M 丙，已知三者最初的溫度不同，吸收相同熱量 後，到達相同的溫度，如表(七)所示。若三鋁塊在升溫 過程中均為固態且無熱量散失，則M 甲：M 乙：M 丙為下 列何者？",
      "options": {
        "A": "_ 1：1：3",
        "B": "1：2：3",
        "C": "2：3：6",
        "D": "3：2：1"
      },
      "correct_answer": "C",
      "explanation": "這題的正確答案是 C。 對應選項內容是「2：3：6」。 先抓題幹關鍵詞，再用刪去法排除不符合條件的選項。 這題來自 106 年會考自然科，建議先回頭確認關鍵概念與題目限制。"
    },
    {
      "number": 31,
      "display_number": 31,
      "page_number": 8,
      "context": "",
      "stem": "若將地表、大氣間的太陽輻射量吸收情形與途徑，以甲、乙、丙、丁表示， 如表(八)所示。在近數十年的科學研究發現，下列何者的增加最有可能是溫室 效應增強的最主要原因？",
      "options": {
        "A": "甲",
        "B": "乙",
        "C": "丙",
        "D": "丁"
      },
      "correct_answer": "A",
      "explanation": "這題的正確答案是 A。 對應選項內容是「甲」。 先抓題幹關鍵詞，再用刪去法排除不符合條件的選項。 這題來自 106 年會考自然科，建議先回頭確認關鍵概念與題目限制。"
    },
    {
      "number": 32,
      "display_number": 32,
      "page_number": 8,
      "context": "",
      "stem": "有一電路裝置如圖(十七)所示，銅線甲、 乙、丙、丁分別與相鄰銅線垂直，且均與 磁場方向垂直，則關於通電時銅線在磁場 中所受的磁力方向，下列何者正確？",
      "options": {
        "A": "銅線甲：向北",
        "B": "銅線乙：向南",
        "C": "銅線丙：向東",
        "D": "銅線丁：向北\n圖(十六)\n圖(十七)\n\u001b\u001a\u0019\n\u0018\u0017\n\u001b\u0016\n\u0015\u0014\u0013\u0012\u0011\n\u0010\u000f\n\u001b\u0016\n\u0015\u0014\u0013\u0012\u0011\n\u0010\u000f\n\u001b\u0016\n\u0018\u0017\u0013\u0012\u0011\n\u0018\u0017\n\u001b\u0016\n\u0010\u000f\u0013\u0012\u0011\n\u000e\n表(六)\n表(七)\n表(八)"
      },
      "correct_answer": "C",
      "explanation": "這題的正確答案是 C。 對應選項內容是「銅線丙：向東」。 先抓題幹關鍵詞，再用刪去法排除不符合條件的選項。 這題來自 106 年會考自然科，建議先回頭確認關鍵概念與題目限制。"
    },
    {
      "number": 33,
      "display_number": 33,
      "page_number": 9,
      "context": "",
      "stem": "小翠進行如圖(十八)步驟的實驗，並根據實驗結果，以量筒中液體的質量與體 積繪圖，並延伸出此液體在不同質量時與體積的關係，小翠繪製出的圖應為 下列何者才正確？",
      "options": {
        "A": "",
        "B": "",
        "C": "",
        "D": ""
      },
      "correct_answer": "D",
      "explanation": "這題的正確答案是 D。 先抓題幹關鍵詞，再用刪去法排除不符合條件的選項。 這題來自 106 年會考自然科，建議先回頭確認關鍵概念與題目限制。"
    },
    {
      "number": 34,
      "display_number": 34,
      "page_number": 9,
      "context": "",
      "stem": "圖(十九)為地球地表附近乾燥大氣的組成百分率圖，根 據此圖，關於大氣氣體的組成，下列敘述何者正確？",
      "options": {
        "A": "以單原子組成的氣體分子，約占78.1%",
        "B": "以雙原子組成的氣體分子，約占99.0%",
        "C": "以單原子組成的氣體分子，約占 0.1%",
        "D": "以雙原子組成的氣體分子，約占79.1%"
      },
      "correct_answer": "B",
      "explanation": "這題的正確答案是 B。 對應選項內容是「以雙原子組成的氣體分子，約占99.0%」。 先抓題幹關鍵詞，再用刪去法排除不符合條件的選項。 這題來自 106 年會考自然科，建議先回頭確認關鍵概念與題目限制。"
    },
    {
      "number": 35,
      "display_number": 35,
      "page_number": 9,
      "context": "",
      "stem": "平靜無風的下午，在許願池上O點丟入一枚 硬幣，使水面上產生一個圓形水波，已知 圓形水波的半徑每秒增加 1 m。若丟入硬幣 前，在水面上距離O點 1 m 及 2 m 的P、Q 兩點，分別有一片落葉，且O、P、Q在同一 直線上，如圖(二十)所示，則硬幣丟入水中 3秒後，兩片落葉的距離約為多少？",
      "options": {
        "A": "3 m",
        "B": "5 m",
        "C": "6 m",
        "D": "9 m\n圖(十八)\n圖(十九)\n圖(二十)\nh\n50mL\n50mL\nh\n2s\n3s\n歸零\n量筒內裝有某液體，並\n置於同一個天平上秤重"
      },
      "correct_answer": "A",
      "explanation": "這題的正確答案是 A。 對應選項內容是「3 m」。 先抓題幹關鍵詞，再用刪去法排除不符合條件的選項。 這題來自 106 年會考自然科，建議先回頭確認關鍵概念與題目限制。"
    },
    {
      "number": 36,
      "display_number": 36,
      "page_number": 10,
      "context": "",
      "stem": "圖(二十一)為人體心臟、肝臟和腎臟之間血液循環的示意圖，箭頭代表血液 流動的方向，甲、乙、丙及丁分別代表不同的血管。根據此圖的血液流動方 向，分別比較甲和乙、丙和丁血液中的尿素濃度，下列何者最合理？",
      "options": {
        "A": "甲＜乙，丙＜丁",
        "B": "甲＜乙，丙＞丁",
        "C": "甲＞乙，丙＜丁",
        "D": "甲＞乙，丙＞丁"
      },
      "correct_answer": "C",
      "explanation": "這題的正確答案是 C。 對應選項內容是「甲＞乙，丙＜丁」。 先抓題幹關鍵詞，再用刪去法排除不符合條件的選項。 這題來自 106 年會考自然科，建議先回頭確認關鍵概念與題目限制。"
    },
    {
      "number": 37,
      "display_number": 37,
      "page_number": 10,
      "context": "",
      "stem": "圖(二十二)為細胞內的某兩對染色體，以甲、乙、丙、丁為代號的示意圖。在正 常狀況下，有關細胞進行分裂與分裂時這些染色體分離的敘述，下列何者正確？",
      "options": {
        "A": "若進行細胞分裂，則甲與乙必分離至不同的細胞中",
        "B": "若進行細胞分裂，則甲與丁必分離至不同的細胞中",
        "C": "若進行減數分裂，則乙與丙必分離至不同的細胞中",
        "D": "若進行減數分裂，則丙與丁必分離至不同的細胞中"
      },
      "correct_answer": "D",
      "explanation": "這題的正確答案是 D。 對應選項內容是「若進行減數分裂，則丙與丁必分離至不同的細胞中」。 先抓題幹關鍵詞，再用刪去法排除不符合條件的選項。 這題來自 106 年會考自然科，建議先回頭確認關鍵概念與題目限制。"
    },
    {
      "number": 38,
      "display_number": 38,
      "page_number": 10,
      "context": "",
      "stem": "將某一食物鏈中生產者及不同階層的消費者所含之 總能量繪製成圖，如圖(二十三)所示。已知此食物鏈 中有一種僅以種子為食的鳥類，則此種鳥類應屬於 下列哪一階層？",
      "options": {
        "A": "甲",
        "B": "乙",
        "C": "丙",
        "D": "丁"
      },
      "correct_answer": "C",
      "explanation": "這題的正確答案是 C。 對應選項內容是「丙」。 先抓題幹關鍵詞，再用刪去法排除不符合條件的選項。 這題來自 106 年會考自然科，建議先回頭確認關鍵概念與題目限制。"
    },
    {
      "number": 39,
      "display_number": 39,
      "page_number": 10,
      "context": "",
      "stem": "小綠在某科學頻道看到全球海底地形圖，其中在大西洋中有一綿延數千公里 的海底山脈。此山脈附近最可能發現下列何者？",
      "options": {
        "A": "有海溝及地震活動",
        "B": "有活躍的擠壓造山運動",
        "C": "地函熱對流的岩漿湧出",
        "D": "地球上最古老的海洋地殼"
      },
      "correct_answer": "C",
      "explanation": "這題的正確答案是 C。 對應選項內容是「地函熱對流的岩漿湧出」。 先抓題幹關鍵詞，再用刪去法排除不符合條件的選項。 這題來自 106 年會考自然科，建議先回頭確認關鍵概念與題目限制。"
    },
    {
      "number": 40,
      "display_number": 40,
      "page_number": 10,
      "context": "",
      "stem": "表(九)為四個同一族元素的部分資訊，其中 的甲、乙、丙、丁四個未知數，何者的正 確數值無法由表中列出的數值推論得知？",
      "options": {
        "A": "甲",
        "B": "乙",
        "C": "丙",
        "D": "丁\n圖(二十一)\n圖(二十二)\n圖(二十三)\n表(九)"
      },
      "correct_answer": "D",
      "explanation": "這題的正確答案是 D。 對應選項內容是「丁\n圖(二十一)\n圖(二十二)\n圖(二十三)\n表(九)」。 先抓題幹關鍵詞，再用刪去法排除不符合條件的選項。 這題來自 106 年會考自然科，建議先回頭確認關鍵概念與題目限制。"
    },
    {
      "number": 41,
      "display_number": 41,
      "page_number": 11,
      "context": "",
      "stem": "如圖(二十四)所示，在一原長為10 cm的彈簧下，吊掛一個重量為600 gw的金屬塊， 靜止平衡時彈簧的全長為15 cm。如圖(二十五)所示，改將此彈簧與金屬塊置於 水平桌面上，彈簧一端連接牆壁，另一端連接金屬塊，對金屬塊施予一個大小 為600 gw，水平向左的拉力，靜止平衡時彈簧全長為14 cm。已知彈簧在實驗後 皆能恢復原長，若忽略彈簧質量的影響，則此金屬塊所受桌面摩擦力的大小及 方向，應為下列何者？",
      "options": {
        "A": "40 gw，方向向左",
        "B": "40 gw，方向向右",
        "C": "120 gw，方向向左",
        "D": "120 gw，方向向右"
      },
      "correct_answer": "D",
      "explanation": "這題的正確答案是 D。 對應選項內容是「120 gw，方向向右」。 先抓題幹關鍵詞，再用刪去法排除不符合條件的選項。 這題來自 106 年會考自然科，建議先回頭確認關鍵概念與題目限制。"
    },
    {
      "number": 42,
      "display_number": 42,
      "page_number": 11,
      "context": "",
      "stem": "如圖(二十六)所示，一正立方體木塊，密度為0.6 g/cm3，置於裝有500 mL水的玻璃 杯中，此時木塊靜止浮於水面，若在此玻璃杯中，再加入500 mL的油，發現液面 上升，但木塊仍靜止浮於液面。已知油與水互不相溶，且油的密度為0.8 g/cm3， 則關於加入油前後的變化，下列敘述何者正確？",
      "options": {
        "A": "木塊沒入液體中的體積變小",
        "B": "木塊沒入液體中的體積變大",
        "C": "木塊在液體中所受的浮力變小",
        "D": "木塊在液體中所受的浮力變大"
      },
      "correct_answer": "B",
      "explanation": "這題的正確答案是 B。 對應選項內容是「木塊沒入液體中的體積變大」。 先抓題幹關鍵詞，再用刪去法排除不符合條件的選項。 這題來自 106 年會考自然科，建議先回頭確認關鍵概念與題目限制。"
    },
    {
      "number": 43,
      "display_number": 43,
      "page_number": 11,
      "context": "",
      "stem": "若在某地垂直水平地面立起一根長度為1 m的 旗竿，並將該地在正午時竿影長度一年的變 化情形記錄於圖(二十七)。根據圖中資訊判 斷，該地一年中受到太陽直射的次數以及發 生的月分，下列何者正確？",
      "options": {
        "A": "一年直射一次，該次發生在6月分",
        "B": "一年直射一次，該次發生在12月分",
        "C": "一年直射兩次，分別發生在1月分和12月分",
        "D": "一年中，該地並不會受到太陽的直射"
      },
      "correct_answer": "D",
      "explanation": "這題的正確答案是 D。 對應選項內容是「一年中，該地並不會受到太陽的直射」。 先抓題幹關鍵詞，再用刪去法排除不符合條件的選項。 這題來自 106 年會考自然科，建議先回頭確認關鍵概念與題目限制。"
    },
    {
      "number": 44,
      "display_number": 44,
      "page_number": 11,
      "context": "",
      "stem": "圖(二十八)為銀杏(學名：Ginkgo biloba)的示意圖，已知 銀杏屬於裸子植物，其種子俗稱為白果，白果及銀杏葉可 用於食用及環境美化。下列關於銀杏的推論，何者正確？",
      "options": {
        "A": "Ginkgo為形容詞",
        "B": "屬於單子葉植物",
        "C": "不具有果實的構造",
        "D": "白果為開花後產生\n圖(二十四)\n圖(二十五)\n圖(二十六)\n圖(二十八)\n圖(二十七)"
      },
      "correct_answer": "C",
      "explanation": "這題的正確答案是 C。 對應選項內容是「不具有果實的構造」。 先抓題幹關鍵詞，再用刪去法排除不符合條件的選項。 這題來自 106 年會考自然科，建議先回頭確認關鍵概念與題目限制。"
    },
    {
      "number": 45,
      "display_number": 45,
      "page_number": 12,
      "context": "",
      "stem": "在某一溫度下，有一杯重量百分濃度40%的檸檬酸水溶液150 g，再加入檸檬酸 65 g攪拌過濾，將濾紙烘乾並秤重後，發現有5 g檸檬酸未溶解。若過程中溶 液溫度均未改變，則在此溫度時檸檬酸的溶解度最接近下列何者？",
      "options": {
        "A": "45 g/100 g水",
        "B": "80 g/100 g水",
        "C": "91 g/100 g水",
        "D": "133 g/100 g水"
      },
      "correct_answer": "D",
      "explanation": "這題的正確答案是 D。 對應選項內容是「133 g/100 g水」。 先抓題幹關鍵詞，再用刪去法排除不符合條件的選項。 這題來自 106 年會考自然科，建議先回頭確認關鍵概念與題目限制。"
    },
    {
      "number": 46,
      "display_number": 46,
      "page_number": 12,
      "context": "",
      "stem": "一電路裝置如圖(二十九)所示，接通電流後，甲、乙、丙 三個電阻器的耗電功率相等，且甲、乙、丙的電阻值分別 為R甲 、R乙 、R丙 ，若導線電阻忽略不計，則下列關係式 何者正確？",
      "options": {
        "A": "R甲＋R乙＝R丙",
        "B": "R甲＋R乙＝4R丙",
        "C": "R甲＝R乙＝R丙",
        "D": "R甲＝R乙＝4R丙\n請閱讀下列敘述後，回答47～48題"
      },
      "correct_answer": "D",
      "explanation": "這題的正確答案是 D。 對應選項內容是「R甲＝R乙＝4R丙\n請閱讀下列敘述後，回答47～48題」。 先抓題幹關鍵詞，再用刪去法排除不符合條件的選項。 這題來自 106 年會考自然科，建議先回頭確認關鍵概念與題目限制。"
    },
    {
      "number": 47,
      "display_number": 47,
      "page_number": 12,
      "context": "",
      "stem": "根據表(十)，小明欲探討「在未提供營養素X時，注射物質Y對大白鼠體重增 加量的影響」，則他應選取下列哪一組合的資料來分析？",
      "options": {
        "A": "甲、乙",
        "B": "甲、丙",
        "C": "乙、丁",
        "D": "丙、丁"
      },
      "correct_answer": "D",
      "explanation": "這題的正確答案是 D。 對應選項內容是「丙、丁」。 先抓題幹關鍵詞，再用刪去法排除不符合條件的選項。 這題來自 106 年會考自然科，建議先回頭確認關鍵概念與題目限制。"
    },
    {
      "number": 48,
      "display_number": 48,
      "page_number": 12,
      "context": "",
      "stem": "根據小明的摘要及圖表判斷，有關營養素X及物質Y在四週內會不會使大白鼠 的體重增加量超過100 gw的推論，下列何者最合理？",
      "options": {
        "A": "營養素X及物質Y皆會",
        "B": "營養素X及物質Y皆不會",
        "C": "營養素X會；物質Y不會",
        "D": "營養素X不會；物質Y會\n以下是小明閱讀某篇研究報告後所作的摘要及圖表：\n某研究員欲探討營養素X和物質Y對大白鼠體重增加量的影響，利用一群條\n件相同的大白鼠，分成四組進行實驗。此研究員先測量各組大白鼠的原始重量，\n各組別再依實驗設計進行不同的處理，如表(十)所示；之後每週都記錄各組大白\n鼠的重量，再把各組每週所測得的重量和原始重量相減，即為各組的體重增加\n量。各組大白鼠在實驗不同週數的體重增加量，如圖(三十)所示。\n表(十)\n圖(二十九)\n圖(三十)\n請閱讀下列敘述後，回答49～50題"
      },
      "correct_answer": "C",
      "explanation": "這題的正確答案是 C。 對應選項內容是「營養素X會；物質Y不會」。 先抓題幹關鍵詞，再用刪去法排除不符合條件的選項。 這題來自 106 年會考自然科，建議先回頭確認關鍵概念與題目限制。"
    },
    {
      "number": 49,
      "display_number": 49,
      "page_number": 13,
      "context": "",
      "stem": "關於文中所提到「電石氣」，應屬於下列哪一類物質？",
      "options": {
        "A": "烴類化合物",
        "B": "金屬氧化物",
        "C": "醇類化合物",
        "D": "無機化合物"
      },
      "correct_answer": "A",
      "explanation": "這題的正確答案是 A。 對應選項內容是「烴類化合物」。 先抓題幹關鍵詞，再用刪去法排除不符合條件的選項。 這題來自 106 年會考自然科，建議先回頭確認關鍵概念與題目限制。"
    },
    {
      "number": 50,
      "display_number": 50,
      "page_number": 13,
      "context": "",
      "stem": "根據本文，磺火捕魚時以電石加水產生的反應，係數平衡後的反應式中， 「兩種反應物係數之和：兩種生成物係數之和」，應為下列何者？",
      "options": {
        "A": "1：1",
        "B": "1：2",
        "C": "2：1",
        "D": "3：2\n請閱讀下列敘述後，回答51～52題"
      },
      "correct_answer": "D",
      "explanation": "這題的正確答案是 D。 對應選項內容是「3：2\n請閱讀下列敘述後，回答51～52題」。 先抓題幹關鍵詞，再用刪去法排除不符合條件的選項。 這題來自 106 年會考自然科，建議先回頭確認關鍵概念與題目限制。"
    },
    {
      "number": 51,
      "display_number": 51,
      "page_number": 13,
      "context": "",
      "stem": "假設路邊的欄杆，兩兩之間的距離均相同。拍攝照片1至拍攝照片2之間的時 間間隔為t 1秒，拍攝照片2至拍攝照片3之間的時間間隔為t 2秒，拍攝照片3至 拍攝照片4之間的時間間隔為t3秒。觀察此四張照片，推測t1、t2、t3之間的大 小關係為下列何者？",
      "options": {
        "A": "t1＞t2＞t3",
        "B": "t1＝t2＜t3",
        "C": "t1＝t2＝t3",
        "D": "t1＜t2＜t3\n「磺火捕魚」是僅存於臺灣北海岸金山一帶的傳統捕魚方式。漁民利\n用電石（主成分為碳化鈣(CaC 2)）加水，反應產生電石氣(C 2H 2)和氫氧化鈣\n（Ca(OH)2），再點燃電石氣，會產生強光，利用魚的趨光性，吸引魚群聚集，\n即可捕撈上船。因為點燃電石氣時會產生強光及巨響，所以此種捕魚方式也俗\n稱「蹦火仔」。"
      },
      "correct_answer": "D",
      "explanation": "這題的正確答案是 D。 對應選項內容是「t1＜t2＜t3\n「磺火捕魚」是僅存於臺灣北海岸金山一帶的傳統捕魚方式。漁民利\n用電石（主成分為碳化鈣(CaC 2)）加水，反應產生電石氣(C 2H 2)和氫氧化鈣\n（Ca(OH)2），再點燃電石氣，會產生強光，利用魚的趨光性，吸引魚群聚集，\n即可捕撈上船。因為點燃電石氣時會產生強光及巨響，所以此種捕魚方式也俗\n稱「蹦火仔」。」。 先抓題幹關鍵詞，再用刪去法排除不符合條件的選項。 這題來自 106 年會考自然科，建議先回頭確認關鍵概念與題目限制。"
    },
    {
      "number": 52,
      "display_number": 52,
      "page_number": 14,
      "context": "圖(三十一)為小育在海邊依序拍攝的四張照片，其角落的標號表示拍攝的先\n後順序，四張照片均在相同位置、相同角度下拍攝，已知照片中的小威在練習投\n籃，騎車的阿祁，在拍攝過程中沿著欄杆旁的筆直道路作「等速度運動」。\n圖(三十一)",
      "stem": "觀察照片右方小威所投出的籃球，在哪兩張照片中，籃球相對於水平地面的 重力位能是相等的？",
      "options": {
        "A": "照片1及照片2",
        "B": "照片2及照片3",
        "C": "照片3及照片4",
        "D": "照片4及照片1\n請閱讀下列敘述後，回答53～54題"
      },
      "correct_answer": "B",
      "explanation": "這題的正確答案是 B。 對應選項內容是「照片2及照片3」。 先把題幹或前面的資料讀完，再圈出題目真正要比對的資訊。 這題來自 106 年會考自然科，建議先回頭確認關鍵概念與題目限制。"
    },
    {
      "number": 53,
      "display_number": 53,
      "page_number": 14,
      "context": "",
      "stem": "若將此次地震的規模與震度資訊繪製成表格，則下列表格中的紀錄何者最合理？",
      "options": {
        "A": "",
        "B": "",
        "C": "",
        "D": ""
      },
      "correct_answer": "A",
      "explanation": "這題的正確答案是 A。 先抓題幹關鍵詞，再用刪去法排除不符合條件的選項。 這題來自 106 年會考自然科，建議先回頭確認關鍵概念與題目限制。"
    },
    {
      "number": 54,
      "display_number": 54,
      "page_number": 14,
      "context": "",
      "stem": "為了解斷層在地下的分布與震源位置，將甲、乙、 丙、丁四個測站的地下構造繪製在圖(三十三)的 剖面示意圖上，下列關於斷層分布與震源位置的 示意圖，何者最合理？",
      "options": {
        "A": "",
        "B": "",
        "C": "",
        "D": "試題結束\n圖(三十二)為某地的斷層與地震測站示意\n圖，\n代表某次地震發生時的震央位置，粗黑\n線則是地震後地表發現的斷層破裂位置，甲、\n乙、丙、丁為四個地震測站。已知此四個地震\n測站與震央皆位於同一直線上，且地震發生\n時，四個地震測站中有三個地震測站感受到明\n顯搖晃，而另一個地震測站雖有儀器紀錄，但\n搖晃程度很小。\n圖(三十二)\n圖(三十三)"
      },
      "correct_answer": "B",
      "explanation": "這題的正確答案是 B。 先抓題幹關鍵詞，再用刪去法排除不符合條件的選項。 這題來自 106 年會考自然科，建議先回頭確認關鍵概念與題目限制。"
    }
  ],
  "issues": [
    {
      "question_number": 1,
      "reason": "parse_incomplete",
      "stem_length": 20,
      "option_count": 0
    },
    {
      "question_number": 2,
      "reason": "parse_incomplete",
      "stem_length": 23,
      "option_count": 0
    },
    {
      "question_number": 3,
      "reason": "parse_incomplete",
      "stem_length": 24,
      "option_count": 0
    },
    {
      "question_number": 4,
      "reason": "parse_incomplete",
      "stem_length": 383,
      "option_count": 0
    }
  ]
}