{
  "title": "會考歷屆練習來源",
  "source_url": "https://cap.rcpet.edu.tw/examination.html",
  "generated_at": "2026-03-29T20:54:10",
  "years": [
    {
      "year": "102",
      "source_url": "https://cap.rcpet.edu.tw/exam/102/102exam.html",
      "answer": {
        "label": "參考答案",
        "url": "https://drive.google.com/file/d/1b3Vusr5_4cJSvDx7HRbENNmmQWEr5kKH/view?usp=drive_link",
        "download_url": "https://drive.google.com/uc?export=download&id=1b3Vusr5_4cJSvDx7HRbENNmmQWEr5kKH",
        "local_path": "C:\\Users\\Good PC\\Desktop\\AI基礎學習平台專案\\data\\cap_practice_sources\\102\\shared\\102_answers.pdf",
        "desktop_pdf_path": "C:\\Users\\Good PC\\Desktop\\國中題庫pdf\\會考歷屆練習\\102\\shared\\102_answers.pdf",
        "word_path": "C:\\Users\\Good PC\\Desktop\\AI基礎學習平台專案\\data\\cap_practice_word\\102\\shared\\102_answers.docx",
        "desktop_word_path": "C:\\Users\\Good PC\\Desktop\\國中題庫\\會考歷屆練習\\102\\shared\\102_answers.docx"
      },
      "explanation": {
        "label": "試題說明",
        "url": "https://drive.google.com/file/d/1VXI00Eb2KozpVJ-dsfrwCBr_vuC9Pfvp/view?usp=drive_link",
        "download_url": "https://drive.google.com/uc?export=download&id=1VXI00Eb2KozpVJ-dsfrwCBr_vuC9Pfvp",
        "local_path": "C:\\Users\\Good PC\\Desktop\\AI基礎學習平台專案\\data\\cap_practice_sources\\102\\shared\\102_explanation.pdf",
        "desktop_pdf_path": "C:\\Users\\Good PC\\Desktop\\國中題庫pdf\\會考歷屆練習\\102\\shared\\102_explanation.pdf",
        "word_path": "C:\\Users\\Good PC\\Desktop\\AI基礎學習平台專案\\data\\cap_practice_word\\102\\shared\\102_explanation.docx",
        "desktop_word_path": "C:\\Users\\Good PC\\Desktop\\國中題庫\\會考歷屆練習\\102\\shared\\102_explanation.docx"
      },
      "subjects": [
        {
          "slug": "chinese",
          "label": "國文",
          "question": {
            "label": "國文科",
            "url": "https://drive.google.com/file/d/1tXmtTYFd4l-IK2J5-uV-C9ZnjXMpMxzC/view?usp=drive_link",
            "download_url": "https://drive.google.com/uc?export=download&id=1tXmtTYFd4l-IK2J5-uV-C9ZnjXMpMxzC",
            "local_path": "C:\\Users\\Good PC\\Desktop\\AI基礎學習平台專案\\data\\cap_practice_sources\\102\\chinese\\102_chinese.pdf",
            "desktop_pdf_path": "C:\\Users\\Good PC\\Desktop\\國中題庫pdf\\會考歷屆練習\\102\\chinese\\102_chinese.pdf",
            "word_path": "C:\\Users\\Good PC\\Desktop\\AI基礎學習平台專案\\data\\cap_practice_word\\102\\chinese\\102_chinese.docx",
            "desktop_word_path": "C:\\Users\\Good PC\\Desktop\\國中題庫\\會考歷屆練習\\102\\chinese\\102_chinese.docx"
          }
        },
        {
          "slug": "english",
          "label": "英語",
          "question": {
            "label": "英語科",
            "url": "https://drive.google.com/file/d/1ZfjE4n22gRv2pcC8rkdVfjS726tE7tgA/view?usp=drive_link",
            "download_url": "https://drive.google.com/uc?export=download&id=1ZfjE4n22gRv2pcC8rkdVfjS726tE7tgA",
            "local_path": "C:\\Users\\Good PC\\Desktop\\AI基礎學習平台專案\\data\\cap_practice_sources\\102\\english\\102_english.pdf",
            "desktop_pdf_path": "C:\\Users\\Good PC\\Desktop\\國中題庫pdf\\會考歷屆練習\\102\\english\\102_english.pdf",
            "word_path": "C:\\Users\\Good PC\\Desktop\\AI基礎學習平台專案\\data\\cap_practice_word\\102\\english\\102_english.docx",
            "desktop_word_path": "C:\\Users\\Good PC\\Desktop\\國中題庫\\會考歷屆練習\\102\\english\\102_english.docx"
          }
        },
        {
          "slug": "math",
          "label": "數學",
          "question": {
            "label": "數學科",
            "url": "https://drive.google.com/file/d/1HBt8CGHtMU4uqygNEuxf_irDtTym6nab/view?usp=drive_link",
            "download_url": "https://drive.google.com/uc?export=download&id=1HBt8CGHtMU4uqygNEuxf_irDtTym6nab",
            "local_path": "C:\\Users\\Good PC\\Desktop\\AI基礎學習平台專案\\data\\cap_practice_sources\\102\\math\\102_math.pdf",
            "desktop_pdf_path": "C:\\Users\\Good PC\\Desktop\\國中題庫pdf\\會考歷屆練習\\102\\math\\102_math.pdf",
            "word_path": "C:\\Users\\Good PC\\Desktop\\AI基礎學習平台專案\\data\\cap_practice_word\\102\\math\\102_math.docx",
            "desktop_word_path": "C:\\Users\\Good PC\\Desktop\\國中題庫\\會考歷屆練習\\102\\math\\102_math.docx"
          }
        },
        {
          "slug": "social",
          "label": "社會",
          "question": {
            "label": "社會科",
            "url": "https://drive.google.com/file/d/1866HSNENTEn9fbBTHt4io5Ky0fKWnFUa/view?usp=drive_link",
            "download_url": "https://drive.google.com/uc?export=download&id=1866HSNENTEn9fbBTHt4io5Ky0fKWnFUa",
            "local_path": "C:\\Users\\Good PC\\Desktop\\AI基礎學習平台專案\\data\\cap_practice_sources\\102\\social\\102_social.pdf",
            "desktop_pdf_path": "C:\\Users\\Good PC\\Desktop\\國中題庫pdf\\會考歷屆練習\\102\\social\\102_social.pdf",
            "word_path": "C:\\Users\\Good PC\\Desktop\\AI基礎學習平台專案\\data\\cap_practice_word\\102\\social\\102_social.docx",
            "desktop_word_path": "C:\\Users\\Good PC\\Desktop\\國中題庫\\會考歷屆練習\\102\\social\\102_social.docx"
          }
        },
        {
          "slug": "science",
          "label": "自然",
          "question": {
            "label": "自然科",
            "url": "https://drive.google.com/file/d/1xuap25S0gTWHIdZR4KCzfnv9Jgejv0JH/view?usp=drive_link",
            "download_url": "https://drive.google.com/uc?export=download&id=1xuap25S0gTWHIdZR4KCzfnv9Jgejv0JH",
            "local_path": "C:\\Users\\Good PC\\Desktop\\AI基礎學習平台專案\\data\\cap_practice_sources\\102\\science\\102_science.pdf",
            "desktop_pdf_path": "C:\\Users\\Good PC\\Desktop\\國中題庫pdf\\會考歷屆練習\\102\\science\\102_science.pdf",
            "word_path": "C:\\Users\\Good PC\\Desktop\\AI基礎學習平台專案\\data\\cap_practice_word\\102\\science\\102_science.docx",
            "desktop_word_path": "C:\\Users\\Good PC\\Desktop\\國中題庫\\會考歷屆練習\\102\\science\\102_science.docx"
          }
        }
      ],
      "issues": []
    },
    {
      "year": "103",
      "source_url": "https://cap.rcpet.edu.tw/exam/103/103exam.html",
      "answer": {
        "label": "參考答案",
        "url": "https://drive.google.com/file/d/1hMiCEiapwaiMyU-VmjvCEvejdAZNLF5X/view?usp=drive_link",
        "download_url": "https://drive.google.com/uc?export=download&id=1hMiCEiapwaiMyU-VmjvCEvejdAZNLF5X",
        "local_path": "C:\\Users\\Good PC\\Desktop\\AI基礎學習平台專案\\data\\cap_practice_sources\\103\\shared\\103_answers.pdf",
        "desktop_pdf_path": "C:\\Users\\Good PC\\Desktop\\國中題庫pdf\\會考歷屆練習\\103\\shared\\103_answers.pdf",
        "word_path": "C:\\Users\\Good PC\\Desktop\\AI基礎學習平台專案\\data\\cap_practice_word\\103\\shared\\103_answers.docx",
        "desktop_word_path": "C:\\Users\\Good PC\\Desktop\\國中題庫\\會考歷屆練習\\103\\shared\\103_answers.docx"
      },
      "explanation": {
        "label": "試題說明",
        "url": "https://drive.google.com/file/d/1LHS0K2YLrDhS_jz2CULl8AnFN23h1x0M/view?usp=drive_link",
        "download_url": "https://drive.google.com/uc?export=download&id=1LHS0K2YLrDhS_jz2CULl8AnFN23h1x0M",
        "local_path": "C:\\Users\\Good PC\\Desktop\\AI基礎學習平台專案\\data\\cap_practice_sources\\103\\shared\\103_explanation.pdf",
        "desktop_pdf_path": "C:\\Users\\Good PC\\Desktop\\國中題庫pdf\\會考歷屆練習\\103\\shared\\103_explanation.pdf",
        "word_path": "C:\\Users\\Good PC\\Desktop\\AI基礎學習平台專案\\data\\cap_practice_word\\103\\shared\\103_explanation.docx",
        "desktop_word_path": "C:\\Users\\Good PC\\Desktop\\國中題庫\\會考歷屆練習\\103\\shared\\103_explanation.docx"
      },
      "subjects": [
        {
          "slug": "chinese",
          "label": "國文",
          "question": {
            "label": "國文科",
            "url": "https://drive.google.com/file/d/1LHS0K2YLrDhS_jz2CULl8AnFN23h1x0M/view?usp=drive_link",
            "download_url": "https://drive.google.com/uc?export=download&id=1LHS0K2YLrDhS_jz2CULl8AnFN23h1x0M",
            "local_path": "C:\\Users\\Good PC\\Desktop\\AI基礎學習平台專案\\data\\cap_practice_sources\\103\\chinese\\103_chinese.pdf",
            "desktop_pdf_path": "C:\\Users\\Good PC\\Desktop\\國中題庫pdf\\會考歷屆練習\\103\\chinese\\103_chinese.pdf",
            "word_path": "C:\\Users\\Good PC\\Desktop\\AI基礎學習平台專案\\data\\cap_practice_word\\103\\chinese\\103_chinese.docx",
            "desktop_word_path": "C:\\Users\\Good PC\\Desktop\\國中題庫\\會考歷屆練習\\103\\chinese\\103_chinese.docx"
          }
        },
        {
          "slug": "english",
          "label": "英語",
          "question": {
            "label": "英語科",
            "url": "https://drive.google.com/file/d/1gY5GMYkN6BRTlYCObVfbN3HsSJD3ua9h/view?usp=drive_link",
            "download_url": "https://drive.google.com/uc?export=download&id=1gY5GMYkN6BRTlYCObVfbN3HsSJD3ua9h",
            "local_path": "C:\\Users\\Good PC\\Desktop\\AI基礎學習平台專案\\data\\cap_practice_sources\\103\\english\\103_english.pdf",
            "desktop_pdf_path": "C:\\Users\\Good PC\\Desktop\\國中題庫pdf\\會考歷屆練習\\103\\english\\103_english.pdf",
            "word_path": "C:\\Users\\Good PC\\Desktop\\AI基礎學習平台專案\\data\\cap_practice_word\\103\\english\\103_english.docx",
            "desktop_word_path": "C:\\Users\\Good PC\\Desktop\\國中題庫\\會考歷屆練習\\103\\english\\103_english.docx"
          }
        },
        {
          "slug": "math",
          "label": "數學",
          "question": {
            "label": "數學科",
            "url": "https://drive.google.com/file/d/1eeCyDq1kTI_tYxt1BJggcJSTNjEhlBZe/view?usp=drive_link",
            "download_url": "https://drive.google.com/uc?export=download&id=1eeCyDq1kTI_tYxt1BJggcJSTNjEhlBZe",
            "local_path": "C:\\Users\\Good PC\\Desktop\\AI基礎學習平台專案\\data\\cap_practice_sources\\103\\math\\103_math.pdf",
            "desktop_pdf_path": "C:\\Users\\Good PC\\Desktop\\國中題庫pdf\\會考歷屆練習\\103\\math\\103_math.pdf",
            "word_path": "C:\\Users\\Good PC\\Desktop\\AI基礎學習平台專案\\data\\cap_practice_word\\103\\math\\103_math.docx",
            "desktop_word_path": "C:\\Users\\Good PC\\Desktop\\國中題庫\\會考歷屆練習\\103\\math\\103_math.docx"
          }
        },
        {
          "slug": "social",
          "label": "社會",
          "question": {
            "label": "社會科",
            "url": "https://drive.google.com/file/d/1Yi7Yjp2BM-DBU0-hoOy8uynjKMttMEW6/view?usp=drive_link",
            "download_url": "https://drive.google.com/uc?export=download&id=1Yi7Yjp2BM-DBU0-hoOy8uynjKMttMEW6",
            "local_path": "C:\\Users\\Good PC\\Desktop\\AI基礎學習平台專案\\data\\cap_practice_sources\\103\\social\\103_social.pdf",
            "desktop_pdf_path": "C:\\Users\\Good PC\\Desktop\\國中題庫pdf\\會考歷屆練習\\103\\social\\103_social.pdf",
            "word_path": "C:\\Users\\Good PC\\Desktop\\AI基礎學習平台專案\\data\\cap_practice_word\\103\\social\\103_social.docx",
            "desktop_word_path": "C:\\Users\\Good PC\\Desktop\\國中題庫\\會考歷屆練習\\103\\social\\103_social.docx"
          }
        },
        {
          "slug": "science",
          "label": "自然",
          "question": {
            "label": "自然科",
            "url": "https://drive.google.com/file/d/1bcO0ssp6S2nFQvnRChlgdnampEDpB7WF/view?usp=drive_link",
            "download_url": "https://drive.google.com/uc?export=download&id=1bcO0ssp6S2nFQvnRChlgdnampEDpB7WF",
            "local_path": "C:\\Users\\Good PC\\Desktop\\AI基礎學習平台專案\\data\\cap_practice_sources\\103\\science\\103_science.pdf",
            "desktop_pdf_path": "C:\\Users\\Good PC\\Desktop\\國中題庫pdf\\會考歷屆練習\\103\\science\\103_science.pdf",
            "word_path": "C:\\Users\\Good PC\\Desktop\\AI基礎學習平台專案\\data\\cap_practice_word\\103\\science\\103_science.docx",
            "desktop_word_path": "C:\\Users\\Good PC\\Desktop\\國中題庫\\會考歷屆練習\\103\\science\\103_science.docx"
          }
        }
      ],
      "issues": []
    },
    {
      "year": "104",
      "source_url": "https://cap.rcpet.edu.tw/exam/104/104exam.html",
      "answer": {
        "label": "參考答案",
        "url": "https://drive.google.com/file/d/1hR_wM3y_h8iEs0lkmjoipsO3yqu-xVkh/view?usp=drive_link",
        "download_url": "https://drive.google.com/uc?export=download&id=1hR_wM3y_h8iEs0lkmjoipsO3yqu-xVkh",
        "local_path": "C:\\Users\\Good PC\\Desktop\\AI基礎學習平台專案\\data\\cap_practice_sources\\104\\shared\\104_answers.pdf",
        "desktop_pdf_path": "C:\\Users\\Good PC\\Desktop\\國中題庫pdf\\會考歷屆練習\\104\\shared\\104_answers.pdf",
        "word_path": "C:\\Users\\Good PC\\Desktop\\AI基礎學習平台專案\\data\\cap_practice_word\\104\\shared\\104_answers.docx",
        "desktop_word_path": "C:\\Users\\Good PC\\Desktop\\國中題庫\\會考歷屆練習\\104\\shared\\104_answers.docx"
      },
      "explanation": {
        "label": "試題說明",
        "url": "https://drive.google.com/file/d/1TWg9u9jOIC0lnwviYQF5qr07OEguBjoN/view?usp=drive_link",
        "download_url": "https://drive.google.com/uc?export=download&id=1TWg9u9jOIC0lnwviYQF5qr07OEguBjoN",
        "local_path": "C:\\Users\\Good PC\\Desktop\\AI基礎學習平台專案\\data\\cap_practice_sources\\104\\shared\\104_explanation.pdf",
        "desktop_pdf_path": "C:\\Users\\Good PC\\Desktop\\國中題庫pdf\\會考歷屆練習\\104\\shared\\104_explanation.pdf",
        "word_path": "C:\\Users\\Good PC\\Desktop\\AI基礎學習平台專案\\data\\cap_practice_word\\104\\shared\\104_explanation.docx",
        "desktop_word_path": "C:\\Users\\Good PC\\Desktop\\國中題庫\\會考歷屆練習\\104\\shared\\104_explanation.docx"
      },
      "subjects": [
        {
          "slug": "chinese",
          "label": "國文",
          "question": {
            "label": "國文科",
            "url": "https://drive.google.com/file/d/12b-9611fJFQ1t-miEOxi_Hp_uJTBqsEJ/view?usp=drive_link",
            "download_url": "https://drive.google.com/uc?export=download&id=12b-9611fJFQ1t-miEOxi_Hp_uJTBqsEJ",
            "local_path": "C:\\Users\\Good PC\\Desktop\\AI基礎學習平台專案\\data\\cap_practice_sources\\104\\chinese\\104_chinese.pdf",
            "desktop_pdf_path": "C:\\Users\\Good PC\\Desktop\\國中題庫pdf\\會考歷屆練習\\104\\chinese\\104_chinese.pdf",
            "word_path": "C:\\Users\\Good PC\\Desktop\\AI基礎學習平台專案\\data\\cap_practice_word\\104\\chinese\\104_chinese.docx",
            "desktop_word_path": "C:\\Users\\Good PC\\Desktop\\國中題庫\\會考歷屆練習\\104\\chinese\\104_chinese.docx"
          }
        },
        {
          "slug": "english",
          "label": "英語",
          "question": {
            "label": "英語（閱讀）",
            "url": "https://drive.google.com/file/d/1T-dPLJfJMjQAK0JNu_kZJi5cyGlEqbtf/view?usp=drive_link",
            "download_url": "https://drive.google.com/uc?export=download&id=1T-dPLJfJMjQAK0JNu_kZJi5cyGlEqbtf",
            "local_path": "C:\\Users\\Good PC\\Desktop\\AI基礎學習平台專案\\data\\cap_practice_sources\\104\\english\\104_english.pdf",
            "desktop_pdf_path": "C:\\Users\\Good PC\\Desktop\\國中題庫pdf\\會考歷屆練習\\104\\english\\104_english.pdf",
            "word_path": "C:\\Users\\Good PC\\Desktop\\AI基礎學習平台專案\\data\\cap_practice_word\\104\\english\\104_english.docx",
            "desktop_word_path": "C:\\Users\\Good PC\\Desktop\\國中題庫\\會考歷屆練習\\104\\english\\104_english.docx"
          }
        },
        {
          "slug": "math",
          "label": "數學",
          "question": {
            "label": "數學科",
            "url": "https://drive.google.com/file/d/1bwFaAAZGPoT3GV1Bz78ExXzFpJhaSyZ4/view?usp=drive_link",
            "download_url": "https://drive.google.com/uc?export=download&id=1bwFaAAZGPoT3GV1Bz78ExXzFpJhaSyZ4",
            "local_path": "C:\\Users\\Good PC\\Desktop\\AI基礎學習平台專案\\data\\cap_practice_sources\\104\\math\\104_math.pdf",
            "desktop_pdf_path": "C:\\Users\\Good PC\\Desktop\\國中題庫pdf\\會考歷屆練習\\104\\math\\104_math.pdf",
            "word_path": "C:\\Users\\Good PC\\Desktop\\AI基礎學習平台專案\\data\\cap_practice_word\\104\\math\\104_math.docx",
            "desktop_word_path": "C:\\Users\\Good PC\\Desktop\\國中題庫\\會考歷屆練習\\104\\math\\104_math.docx"
          }
        },
        {
          "slug": "social",
          "label": "社會",
          "question": {
            "label": "社會科",
            "url": "https://drive.google.com/file/d/1iH2RqmpilJ9FcMNC4_QruSUKUhhcCzKx/view?usp=drive_link",
            "download_url": "https://drive.google.com/uc?export=download&id=1iH2RqmpilJ9FcMNC4_QruSUKUhhcCzKx",
            "local_path": "C:\\Users\\Good PC\\Desktop\\AI基礎學習平台專案\\data\\cap_practice_sources\\104\\social\\104_social.pdf",
            "desktop_pdf_path": "C:\\Users\\Good PC\\Desktop\\國中題庫pdf\\會考歷屆練習\\104\\social\\104_social.pdf",
            "word_path": "C:\\Users\\Good PC\\Desktop\\AI基礎學習平台專案\\data\\cap_practice_word\\104\\social\\104_social.docx",
            "desktop_word_path": "C:\\Users\\Good PC\\Desktop\\國中題庫\\會考歷屆練習\\104\\social\\104_social.docx"
          }
        },
        {
          "slug": "science",
          "label": "自然",
          "question": {
            "label": "自然科",
            "url": "https://drive.google.com/file/d/1_71XW7z1fj3jCzjTQsKIrkEDHyRxCzGE/view?usp=drive_link",
            "download_url": "https://drive.google.com/uc?export=download&id=1_71XW7z1fj3jCzjTQsKIrkEDHyRxCzGE",
            "local_path": "C:\\Users\\Good PC\\Desktop\\AI基礎學習平台專案\\data\\cap_practice_sources\\104\\science\\104_science.pdf",
            "desktop_pdf_path": "C:\\Users\\Good PC\\Desktop\\國中題庫pdf\\會考歷屆練習\\104\\science\\104_science.pdf",
            "word_path": "C:\\Users\\Good PC\\Desktop\\AI基礎學習平台專案\\data\\cap_practice_word\\104\\science\\104_science.docx",
            "desktop_word_path": "C:\\Users\\Good PC\\Desktop\\國中題庫\\會考歷屆練習\\104\\science\\104_science.docx"
          }
        }
      ],
      "issues": []
    },
    {
      "year": "105",
      "source_url": "https://cap.rcpet.edu.tw/exam/105/105exam.html",
      "answer": {
        "label": "參考答案",
        "url": "https://drive.google.com/file/d/15bDpOsfOw4ucIgdCwH5tggq7TVTlbap7/view?usp=drive_link",
        "download_url": "https://drive.google.com/uc?export=download&id=15bDpOsfOw4ucIgdCwH5tggq7TVTlbap7",
        "local_path": "C:\\Users\\Good PC\\Desktop\\AI基礎學習平台專案\\data\\cap_practice_sources\\105\\shared\\105_answers.pdf",
        "desktop_pdf_path": "C:\\Users\\Good PC\\Desktop\\國中題庫pdf\\會考歷屆練習\\105\\shared\\105_answers.pdf",
        "word_path": "C:\\Users\\Good PC\\Desktop\\AI基礎學習平台專案\\data\\cap_practice_word\\105\\shared\\105_answers.docx",
        "desktop_word_path": "C:\\Users\\Good PC\\Desktop\\國中題庫\\會考歷屆練習\\105\\shared\\105_answers.docx"
      },
      "explanation": {
        "label": "試題說明",
        "url": "https://drive.google.com/file/d/1R8cJWW0vwBg5hJI8K62tkG4L8XpN63a_/view?usp=drive_link",
        "download_url": "https://drive.google.com/uc?export=download&id=1R8cJWW0vwBg5hJI8K62tkG4L8XpN63a_",
        "local_path": "C:\\Users\\Good PC\\Desktop\\AI基礎學習平台專案\\data\\cap_practice_sources\\105\\shared\\105_explanation.pdf",
        "desktop_pdf_path": "C:\\Users\\Good PC\\Desktop\\國中題庫pdf\\會考歷屆練習\\105\\shared\\105_explanation.pdf",
        "word_path": "C:\\Users\\Good PC\\Desktop\\AI基礎學習平台專案\\data\\cap_practice_word\\105\\shared\\105_explanation.docx",
        "desktop_word_path": "C:\\Users\\Good PC\\Desktop\\國中題庫\\會考歷屆練習\\105\\shared\\105_explanation.docx"
      },
      "subjects": [
        {
          "slug": "chinese",
          "label": "國文",
          "question": {
            "label": "國文科",
            "url": "https://drive.google.com/file/d/1gpds3aItngE56h2nuTCYZTPWB0x_ugUn/view?usp=drive_link",
            "download_url": "https://drive.google.com/uc?export=download&id=1gpds3aItngE56h2nuTCYZTPWB0x_ugUn",
            "local_path": "C:\\Users\\Good PC\\Desktop\\AI基礎學習平台專案\\data\\cap_practice_sources\\105\\chinese\\105_chinese.pdf",
            "desktop_pdf_path": "C:\\Users\\Good PC\\Desktop\\國中題庫pdf\\會考歷屆練習\\105\\chinese\\105_chinese.pdf",
            "word_path": "C:\\Users\\Good PC\\Desktop\\AI基礎學習平台專案\\data\\cap_practice_word\\105\\chinese\\105_chinese.docx",
            "desktop_word_path": "C:\\Users\\Good PC\\Desktop\\國中題庫\\會考歷屆練習\\105\\chinese\\105_chinese.docx"
          }
        },
        {
          "slug": "english",
          "label": "英語",
          "question": {
            "label": "英語（閱讀）",
            "url": "https://drive.google.com/file/d/1obYGSaLt_OTg1wVya-k__JAgZXmuKc7h/view?usp=drive_link",
            "download_url": "https://drive.google.com/uc?export=download&id=1obYGSaLt_OTg1wVya-k__JAgZXmuKc7h",
            "local_path": "C:\\Users\\Good PC\\Desktop\\AI基礎學習平台專案\\data\\cap_practice_sources\\105\\english\\105_english.pdf",
            "desktop_pdf_path": "C:\\Users\\Good PC\\Desktop\\國中題庫pdf\\會考歷屆練習\\105\\english\\105_english.pdf",
            "word_path": "C:\\Users\\Good PC\\Desktop\\AI基礎學習平台專案\\data\\cap_practice_word\\105\\english\\105_english.docx",
            "desktop_word_path": "C:\\Users\\Good PC\\Desktop\\國中題庫\\會考歷屆練習\\105\\english\\105_english.docx"
          }
        },
        {
          "slug": "math",
          "label": "數學",
          "question": {
            "label": "數學科",
            "url": "https://drive.google.com/file/d/1dmMcIsjV1wA-UmKsQ-DiiwY-BzQx-lA1/view?usp=drive_link",
            "download_url": "https://drive.google.com/uc?export=download&id=1dmMcIsjV1wA-UmKsQ-DiiwY-BzQx-lA1",
            "local_path": "C:\\Users\\Good PC\\Desktop\\AI基礎學習平台專案\\data\\cap_practice_sources\\105\\math\\105_math.pdf",
            "desktop_pdf_path": "C:\\Users\\Good PC\\Desktop\\國中題庫pdf\\會考歷屆練習\\105\\math\\105_math.pdf",
            "word_path": "C:\\Users\\Good PC\\Desktop\\AI基礎學習平台專案\\data\\cap_practice_word\\105\\math\\105_math.docx",
            "desktop_word_path": "C:\\Users\\Good PC\\Desktop\\國中題庫\\會考歷屆練習\\105\\math\\105_math.docx"
          }
        },
        {
          "slug": "social",
          "label": "社會",
          "question": {
            "label": "社會科",
            "url": "https://drive.google.com/file/d/1wbHfZbLPrt3PLizRBuCgU_AX2K6-dv1V/view?usp=drive_link",
            "download_url": "https://drive.google.com/uc?export=download&id=1wbHfZbLPrt3PLizRBuCgU_AX2K6-dv1V",
            "local_path": "C:\\Users\\Good PC\\Desktop\\AI基礎學習平台專案\\data\\cap_practice_sources\\105\\social\\105_social.pdf",
            "desktop_pdf_path": "C:\\Users\\Good PC\\Desktop\\國中題庫pdf\\會考歷屆練習\\105\\social\\105_social.pdf",
            "word_path": "C:\\Users\\Good PC\\Desktop\\AI基礎學習平台專案\\data\\cap_practice_word\\105\\social\\105_social.docx",
            "desktop_word_path": "C:\\Users\\Good PC\\Desktop\\國中題庫\\會考歷屆練習\\105\\social\\105_social.docx"
          }
        },
        {
          "slug": "science",
          "label": "自然",
          "question": {
            "label": "自然科",
            "url": "https://drive.google.com/file/d/1MXLxdpcaTtIzNIGRHk_DBMTb5lloTDUN/view?usp=drive_link",
            "download_url": "https://drive.google.com/uc?export=download&id=1MXLxdpcaTtIzNIGRHk_DBMTb5lloTDUN",
            "local_path": "C:\\Users\\Good PC\\Desktop\\AI基礎學習平台專案\\data\\cap_practice_sources\\105\\science\\105_science.pdf",
            "desktop_pdf_path": "C:\\Users\\Good PC\\Desktop\\國中題庫pdf\\會考歷屆練習\\105\\science\\105_science.pdf",
            "word_path": "C:\\Users\\Good PC\\Desktop\\AI基礎學習平台專案\\data\\cap_practice_word\\105\\science\\105_science.docx",
            "desktop_word_path": "C:\\Users\\Good PC\\Desktop\\國中題庫\\會考歷屆練習\\105\\science\\105_science.docx"
          }
        }
      ],
      "issues": [
        "duplicate_label:參考答案:2",
        "duplicate_label:國文科:2",
        "duplicate_label:數學科:2",
        "duplicate_label:第一題:2",
        "duplicate_label:第二題:2"
      ]
    },
    {
      "year": "106",
      "source_url": "https://cap.rcpet.edu.tw/exam/106/106exam.html",
      "answer": {
        "label": "參考答案",
        "url": "https://drive.google.com/file/d/1SDrO_xG9MG6Kmcg1H9ibY_NM410de9VF/view?usp=drive_link",
        "download_url": "https://drive.google.com/uc?export=download&id=1SDrO_xG9MG6Kmcg1H9ibY_NM410de9VF",
        "local_path": "C:\\Users\\Good PC\\Desktop\\AI基礎學習平台專案\\data\\cap_practice_sources\\106\\shared\\106_answers.pdf",
        "desktop_pdf_path": "C:\\Users\\Good PC\\Desktop\\國中題庫pdf\\會考歷屆練習\\106\\shared\\106_answers.pdf",
        "word_path": "C:\\Users\\Good PC\\Desktop\\AI基礎學習平台專案\\data\\cap_practice_word\\106\\shared\\106_answers.docx",
        "desktop_word_path": "C:\\Users\\Good PC\\Desktop\\國中題庫\\會考歷屆練習\\106\\shared\\106_answers.docx"
      },
      "explanation": {
        "label": "試題說明",
        "url": "https://drive.google.com/file/d/16HOh22LGO2laMdfIZSpXIQG-lfADP7LB/view?usp=drive_link",
        "download_url": "https://drive.google.com/uc?export=download&id=16HOh22LGO2laMdfIZSpXIQG-lfADP7LB",
        "local_path": "C:\\Users\\Good PC\\Desktop\\AI基礎學習平台專案\\data\\cap_practice_sources\\106\\shared\\106_explanation.pdf",
        "desktop_pdf_path": "C:\\Users\\Good PC\\Desktop\\國中題庫pdf\\會考歷屆練習\\106\\shared\\106_explanation.pdf",
        "word_path": "C:\\Users\\Good PC\\Desktop\\AI基礎學習平台專案\\data\\cap_practice_word\\106\\shared\\106_explanation.docx",
        "desktop_word_path": "C:\\Users\\Good PC\\Desktop\\國中題庫\\會考歷屆練習\\106\\shared\\106_explanation.docx"
      },
      "subjects": [
        {
          "slug": "chinese",
          "label": "國文",
          "question": {
            "label": "國文科",
            "url": "https://drive.google.com/file/d/1lkJulMy3LDaPetCw2kV0eU1K1uiK2Uqv/view?usp=drive_link",
            "download_url": "https://drive.google.com/uc?export=download&id=1lkJulMy3LDaPetCw2kV0eU1K1uiK2Uqv",
            "local_path": "C:\\Users\\Good PC\\Desktop\\AI基礎學習平台專案\\data\\cap_practice_sources\\106\\chinese\\106_chinese.pdf",
            "desktop_pdf_path": "C:\\Users\\Good PC\\Desktop\\國中題庫pdf\\會考歷屆練習\\106\\chinese\\106_chinese.pdf",
            "word_path": "C:\\Users\\Good PC\\Desktop\\AI基礎學習平台專案\\data\\cap_practice_word\\106\\chinese\\106_chinese.docx",
            "desktop_word_path": "C:\\Users\\Good PC\\Desktop\\國中題庫\\會考歷屆練習\\106\\chinese\\106_chinese.docx"
          }
        },
        {
          "slug": "english",
          "label": "英語",
          "question": {
            "label": "英語（閱讀）",
            "url": "https://drive.google.com/file/d/1hbGHVdkMmiWxIZL1c5OTO9RUUZPgMUjB/view?usp=drive_link",
            "download_url": "https://drive.google.com/uc?export=download&id=1hbGHVdkMmiWxIZL1c5OTO9RUUZPgMUjB",
            "local_path": "C:\\Users\\Good PC\\Desktop\\AI基礎學習平台專案\\data\\cap_practice_sources\\106\\english\\106_english.pdf",
            "desktop_pdf_path": "C:\\Users\\Good PC\\Desktop\\國中題庫pdf\\會考歷屆練習\\106\\english\\106_english.pdf",
            "word_path": "C:\\Users\\Good PC\\Desktop\\AI基礎學習平台專案\\data\\cap_practice_word\\106\\english\\106_english.docx",
            "desktop_word_path": "C:\\Users\\Good PC\\Desktop\\國中題庫\\會考歷屆練習\\106\\english\\106_english.docx"
          }
        },
        {
          "slug": "math",
          "label": "數學",
          "question": {
            "label": "數學科",
            "url": "https://drive.google.com/file/d/10JGzIlDxgOyUmcVZVn3E5os8trXbcorr/view?usp=drive_link",
            "download_url": "https://drive.google.com/uc?export=download&id=10JGzIlDxgOyUmcVZVn3E5os8trXbcorr",
            "local_path": "C:\\Users\\Good PC\\Desktop\\AI基礎學習平台專案\\data\\cap_practice_sources\\106\\math\\106_math.pdf",
            "desktop_pdf_path": "C:\\Users\\Good PC\\Desktop\\國中題庫pdf\\會考歷屆練習\\106\\math\\106_math.pdf",
            "word_path": "C:\\Users\\Good PC\\Desktop\\AI基礎學習平台專案\\data\\cap_practice_word\\106\\math\\106_math.docx",
            "desktop_word_path": "C:\\Users\\Good PC\\Desktop\\國中題庫\\會考歷屆練習\\106\\math\\106_math.docx"
          }
        },
        {
          "slug": "social",
          "label": "社會",
          "question": {
            "label": "社會科",
            "url": "https://drive.google.com/file/d/1a2FJG15x_aFlDwJEe377et0cau-yYKK-/view?usp=drive_link",
            "download_url": "https://drive.google.com/uc?export=download&id=1a2FJG15x_aFlDwJEe377et0cau-yYKK-",
            "local_path": "C:\\Users\\Good PC\\Desktop\\AI基礎學習平台專案\\data\\cap_practice_sources\\106\\social\\106_social.pdf",
            "desktop_pdf_path": "C:\\Users\\Good PC\\Desktop\\國中題庫pdf\\會考歷屆練習\\106\\social\\106_social.pdf",
            "word_path": "C:\\Users\\Good PC\\Desktop\\AI基礎學習平台專案\\data\\cap_practice_word\\106\\social\\106_social.docx",
            "desktop_word_path": "C:\\Users\\Good PC\\Desktop\\國中題庫\\會考歷屆練習\\106\\social\\106_social.docx"
          }
        },
        {
          "slug": "science",
          "label": "自然",
          "question": {
            "label": "自然科",
            "url": "https://drive.google.com/file/d/1nKOX2Y_Lc97oRP0CNdibx3sdWo4zWj2s/view?usp=drive_link",
            "download_url": "https://drive.google.com/uc?export=download&id=1nKOX2Y_Lc97oRP0CNdibx3sdWo4zWj2s",
            "local_path": "C:\\Users\\Good PC\\Desktop\\AI基礎學習平台專案\\data\\cap_practice_sources\\106\\science\\106_science.pdf",
            "desktop_pdf_path": "C:\\Users\\Good PC\\Desktop\\國中題庫pdf\\會考歷屆練習\\106\\science\\106_science.pdf",
            "word_path": "C:\\Users\\Good PC\\Desktop\\AI基礎學習平台專案\\data\\cap_practice_word\\106\\science\\106_science.docx",
            "desktop_word_path": "C:\\Users\\Good PC\\Desktop\\國中題庫\\會考歷屆練習\\106\\science\\106_science.docx"
          }
        }
      ],
      "issues": []
    },
    {
      "year": "107",
      "source_url": "https://cap.rcpet.edu.tw/exam/107/107exam.html",
      "answer": {
        "label": "參考答案",
        "url": "https://drive.google.com/file/d/1XigR8bMEJoG6lwe8yhsbKpHn3MHfUSeY/view?usp=drive_link",
        "download_url": "https://drive.google.com/uc?export=download&id=1XigR8bMEJoG6lwe8yhsbKpHn3MHfUSeY",
        "local_path": "C:\\Users\\Good PC\\Desktop\\AI基礎學習平台專案\\data\\cap_practice_sources\\107\\shared\\107_answers.pdf",
        "desktop_pdf_path": "C:\\Users\\Good PC\\Desktop\\國中題庫pdf\\會考歷屆練習\\107\\shared\\107_answers.pdf",
        "word_path": "C:\\Users\\Good PC\\Desktop\\AI基礎學習平台專案\\data\\cap_practice_word\\107\\shared\\107_answers.docx",
        "desktop_word_path": "C:\\Users\\Good PC\\Desktop\\國中題庫\\會考歷屆練習\\107\\shared\\107_answers.docx"
      },
      "explanation": {
        "label": "試題說明",
        "url": "https://drive.google.com/file/d/1uYkpWEpmYaoF8vFrMoEcuGOeyqOPqWjA/view?usp=drive_link",
        "download_url": "https://drive.google.com/uc?export=download&id=1uYkpWEpmYaoF8vFrMoEcuGOeyqOPqWjA",
        "local_path": "C:\\Users\\Good PC\\Desktop\\AI基礎學習平台專案\\data\\cap_practice_sources\\107\\shared\\107_explanation.pdf",
        "desktop_pdf_path": "C:\\Users\\Good PC\\Desktop\\國中題庫pdf\\會考歷屆練習\\107\\shared\\107_explanation.pdf",
        "word_path": "C:\\Users\\Good PC\\Desktop\\AI基礎學習平台專案\\data\\cap_practice_word\\107\\shared\\107_explanation.docx",
        "desktop_word_path": "C:\\Users\\Good PC\\Desktop\\國中題庫\\會考歷屆練習\\107\\shared\\107_explanation.docx"
      },
      "subjects": [
        {
          "slug": "chinese",
          "label": "國文",
          "question": {
            "label": "國文科",
            "url": "https://drive.google.com/file/d/1o9HsmNT7ydexWB8IhdEeOJ47MEaSN6jq/view?usp=drive_link",
            "download_url": "https://drive.google.com/uc?export=download&id=1o9HsmNT7ydexWB8IhdEeOJ47MEaSN6jq",
            "local_path": "C:\\Users\\Good PC\\Desktop\\AI基礎學習平台專案\\data\\cap_practice_sources\\107\\chinese\\107_chinese.pdf",
            "desktop_pdf_path": "C:\\Users\\Good PC\\Desktop\\國中題庫pdf\\會考歷屆練習\\107\\chinese\\107_chinese.pdf",
            "word_path": "C:\\Users\\Good PC\\Desktop\\AI基礎學習平台專案\\data\\cap_practice_word\\107\\chinese\\107_chinese.docx",
            "desktop_word_path": "C:\\Users\\Good PC\\Desktop\\國中題庫\\會考歷屆練習\\107\\chinese\\107_chinese.docx"
          }
        },
        {
          "slug": "english",
          "label": "英語",
          "question": {
            "label": "英語（閱讀）",
            "url": "https://drive.google.com/file/d/1ToSEBw4hLa4GGonGdUUf70Dibg4juSDw/view?usp=drive_link",
            "download_url": "https://drive.google.com/uc?export=download&id=1ToSEBw4hLa4GGonGdUUf70Dibg4juSDw",
            "local_path": "C:\\Users\\Good PC\\Desktop\\AI基礎學習平台專案\\data\\cap_practice_sources\\107\\english\\107_english.pdf",
            "desktop_pdf_path": "C:\\Users\\Good PC\\Desktop\\國中題庫pdf\\會考歷屆練習\\107\\english\\107_english.pdf",
            "word_path": "C:\\Users\\Good PC\\Desktop\\AI基礎學習平台專案\\data\\cap_practice_word\\107\\english\\107_english.docx",
            "desktop_word_path": "C:\\Users\\Good PC\\Desktop\\國中題庫\\會考歷屆練習\\107\\english\\107_english.docx"
          }
        },
        {
          "slug": "math",
          "label": "數學",
          "question": {
            "label": "數學科",
            "url": "https://drive.google.com/file/d/1331V76tWuKofLTQ2Lx4U_pEJ6ZR4SG0J/view?usp=drive_link",
            "download_url": "https://drive.google.com/uc?export=download&id=1331V76tWuKofLTQ2Lx4U_pEJ6ZR4SG0J",
            "local_path": "C:\\Users\\Good PC\\Desktop\\AI基礎學習平台專案\\data\\cap_practice_sources\\107\\math\\107_math.pdf",
            "desktop_pdf_path": "C:\\Users\\Good PC\\Desktop\\國中題庫pdf\\會考歷屆練習\\107\\math\\107_math.pdf",
            "word_path": "C:\\Users\\Good PC\\Desktop\\AI基礎學習平台專案\\data\\cap_practice_word\\107\\math\\107_math.docx",
            "desktop_word_path": "C:\\Users\\Good PC\\Desktop\\國中題庫\\會考歷屆練習\\107\\math\\107_math.docx"
          }
        },
        {
          "slug": "social",
          "label": "社會",
          "question": {
            "label": "社會科",
            "url": "https://drive.google.com/file/d/13zTtdH_y-6OR5RDSvMfEKDSRyZe-pqPU/view?usp=drive_link",
            "download_url": "https://drive.google.com/uc?export=download&id=13zTtdH_y-6OR5RDSvMfEKDSRyZe-pqPU",
            "local_path": "C:\\Users\\Good PC\\Desktop\\AI基礎學習平台專案\\data\\cap_practice_sources\\107\\social\\107_social.pdf",
            "desktop_pdf_path": "C:\\Users\\Good PC\\Desktop\\國中題庫pdf\\會考歷屆練習\\107\\social\\107_social.pdf",
            "word_path": "C:\\Users\\Good PC\\Desktop\\AI基礎學習平台專案\\data\\cap_practice_word\\107\\social\\107_social.docx",
            "desktop_word_path": "C:\\Users\\Good PC\\Desktop\\國中題庫\\會考歷屆練習\\107\\social\\107_social.docx"
          }
        },
        {
          "slug": "science",
          "label": "自然",
          "question": {
            "label": "自然科",
            "url": "https://drive.google.com/file/d/1liuOGMSy_z_57Gbu9psuWPxQw_8oAt32/view?usp=drive_link",
            "download_url": "https://drive.google.com/uc?export=download&id=1liuOGMSy_z_57Gbu9psuWPxQw_8oAt32",
            "local_path": "C:\\Users\\Good PC\\Desktop\\AI基礎學習平台專案\\data\\cap_practice_sources\\107\\science\\107_science.pdf",
            "desktop_pdf_path": "C:\\Users\\Good PC\\Desktop\\國中題庫pdf\\會考歷屆練習\\107\\science\\107_science.pdf",
            "word_path": "C:\\Users\\Good PC\\Desktop\\AI基礎學習平台專案\\data\\cap_practice_word\\107\\science\\107_science.docx",
            "desktop_word_path": "C:\\Users\\Good PC\\Desktop\\國中題庫\\會考歷屆練習\\107\\science\\107_science.docx"
          }
        }
      ],
      "issues": []
    },
    {
      "year": "108",
      "source_url": "https://cap.rcpet.edu.tw/exam/108/108exam.html",
      "answer": {
        "label": "參考答案",
        "url": "https://drive.google.com/file/d/1M5ObFB8NhhzocLtxc11O2VREq_h1-YBb/view?usp=drive_link",
        "download_url": "https://drive.google.com/uc?export=download&id=1M5ObFB8NhhzocLtxc11O2VREq_h1-YBb",
        "local_path": "C:\\Users\\Good PC\\Desktop\\AI基礎學習平台專案\\data\\cap_practice_sources\\108\\shared\\108_answers.pdf",
        "desktop_pdf_path": "C:\\Users\\Good PC\\Desktop\\國中題庫pdf\\會考歷屆練習\\108\\shared\\108_answers.pdf",
        "word_path": "C:\\Users\\Good PC\\Desktop\\AI基礎學習平台專案\\data\\cap_practice_word\\108\\shared\\108_answers.docx",
        "desktop_word_path": "C:\\Users\\Good PC\\Desktop\\國中題庫\\會考歷屆練習\\108\\shared\\108_answers.docx"
      },
      "explanation": {
        "label": "試題說明",
        "url": "https://drive.google.com/file/d/1G4brkSQwKSVS960xoiTAQpAhO8V-q-WR/view?usp=drive_link",
        "download_url": "https://drive.google.com/uc?export=download&id=1G4brkSQwKSVS960xoiTAQpAhO8V-q-WR",
        "local_path": "C:\\Users\\Good PC\\Desktop\\AI基礎學習平台專案\\data\\cap_practice_sources\\108\\shared\\108_explanation.pdf",
        "desktop_pdf_path": "C:\\Users\\Good PC\\Desktop\\國中題庫pdf\\會考歷屆練習\\108\\shared\\108_explanation.pdf",
        "word_path": "C:\\Users\\Good PC\\Desktop\\AI基礎學習平台專案\\data\\cap_practice_word\\108\\shared\\108_explanation.docx",
        "desktop_word_path": "C:\\Users\\Good PC\\Desktop\\國中題庫\\會考歷屆練習\\108\\shared\\108_explanation.docx"
      },
      "subjects": [
        {
          "slug": "chinese",
          "label": "國文",
          "question": {
            "label": "國文科",
            "url": "https://drive.google.com/file/d/1kv7IPubkZqdd4Sm9NJQ4TneXHS4Nj5Qu/view?usp=drive_link",
            "download_url": "https://drive.google.com/uc?export=download&id=1kv7IPubkZqdd4Sm9NJQ4TneXHS4Nj5Qu",
            "local_path": "C:\\Users\\Good PC\\Desktop\\AI基礎學習平台專案\\data\\cap_practice_sources\\108\\chinese\\108_chinese.pdf",
            "desktop_pdf_path": "C:\\Users\\Good PC\\Desktop\\國中題庫pdf\\會考歷屆練習\\108\\chinese\\108_chinese.pdf",
            "word_path": "C:\\Users\\Good PC\\Desktop\\AI基礎學習平台專案\\data\\cap_practice_word\\108\\chinese\\108_chinese.docx",
            "desktop_word_path": "C:\\Users\\Good PC\\Desktop\\國中題庫\\會考歷屆練習\\108\\chinese\\108_chinese.docx"
          }
        },
        {
          "slug": "english",
          "label": "英語",
          "question": {
            "label": "英語（閱讀）",
            "url": "https://drive.google.com/file/d/1z8bQ38BFxWvXiHr_yxD6pv9UXy8sxW6v/view?usp=drive_link",
            "download_url": "https://drive.google.com/uc?export=download&id=1z8bQ38BFxWvXiHr_yxD6pv9UXy8sxW6v",
            "local_path": "C:\\Users\\Good PC\\Desktop\\AI基礎學習平台專案\\data\\cap_practice_sources\\108\\english\\108_english.pdf",
            "desktop_pdf_path": "C:\\Users\\Good PC\\Desktop\\國中題庫pdf\\會考歷屆練習\\108\\english\\108_english.pdf",
            "word_path": "C:\\Users\\Good PC\\Desktop\\AI基礎學習平台專案\\data\\cap_practice_word\\108\\english\\108_english.docx",
            "desktop_word_path": "C:\\Users\\Good PC\\Desktop\\國中題庫\\會考歷屆練習\\108\\english\\108_english.docx"
          }
        },
        {
          "slug": "math",
          "label": "數學",
          "question": {
            "label": "數學科",
            "url": "https://drive.google.com/file/d/1ouI9tIEJETAGqzh4V1OwB1t83ouA-CaH/view?usp=drive_link",
            "download_url": "https://drive.google.com/uc?export=download&id=1ouI9tIEJETAGqzh4V1OwB1t83ouA-CaH",
            "local_path": "C:\\Users\\Good PC\\Desktop\\AI基礎學習平台專案\\data\\cap_practice_sources\\108\\math\\108_math.pdf",
            "desktop_pdf_path": "C:\\Users\\Good PC\\Desktop\\國中題庫pdf\\會考歷屆練習\\108\\math\\108_math.pdf",
            "word_path": "C:\\Users\\Good PC\\Desktop\\AI基礎學習平台專案\\data\\cap_practice_word\\108\\math\\108_math.docx",
            "desktop_word_path": "C:\\Users\\Good PC\\Desktop\\國中題庫\\會考歷屆練習\\108\\math\\108_math.docx"
          }
        },
        {
          "slug": "social",
          "label": "社會",
          "question": {
            "label": "社會科",
            "url": "https://drive.google.com/file/d/1ZVi5WqoWsZOq83HmVSoiuy4nCxNLD54o/view?usp=drive_link",
            "download_url": "https://drive.google.com/uc?export=download&id=1ZVi5WqoWsZOq83HmVSoiuy4nCxNLD54o",
            "local_path": "C:\\Users\\Good PC\\Desktop\\AI基礎學習平台專案\\data\\cap_practice_sources\\108\\social\\108_social.pdf",
            "desktop_pdf_path": "C:\\Users\\Good PC\\Desktop\\國中題庫pdf\\會考歷屆練習\\108\\social\\108_social.pdf",
            "word_path": "C:\\Users\\Good PC\\Desktop\\AI基礎學習平台專案\\data\\cap_practice_word\\108\\social\\108_social.docx",
            "desktop_word_path": "C:\\Users\\Good PC\\Desktop\\國中題庫\\會考歷屆練習\\108\\social\\108_social.docx"
          }
        },
        {
          "slug": "science",
          "label": "自然",
          "question": {
            "label": "自然科",
            "url": "https://drive.google.com/file/d/1BXf0z9hqcmlnefKk1XKLQQp1ec6V1azI/view?usp=drive_link",
            "download_url": "https://drive.google.com/uc?export=download&id=1BXf0z9hqcmlnefKk1XKLQQp1ec6V1azI",
            "local_path": "C:\\Users\\Good PC\\Desktop\\AI基礎學習平台專案\\data\\cap_practice_sources\\108\\science\\108_science.pdf",
            "desktop_pdf_path": "C:\\Users\\Good PC\\Desktop\\國中題庫pdf\\會考歷屆練習\\108\\science\\108_science.pdf",
            "word_path": "C:\\Users\\Good PC\\Desktop\\AI基礎學習平台專案\\data\\cap_practice_word\\108\\science\\108_science.docx",
            "desktop_word_path": "C:\\Users\\Good PC\\Desktop\\國中題庫\\會考歷屆練習\\108\\science\\108_science.docx"
          }
        }
      ],
      "issues": []
    },
    {
      "year": "109",
      "source_url": "https://cap.rcpet.edu.tw/exam/109/109exam.html",
      "answer": {
        "label": "參考答案",
        "url": "https://drive.google.com/file/d/1zj_iw_7T3M6BgmGZkFOIIGNghr02dWPk/view?usp=drive_link",
        "download_url": "https://drive.google.com/uc?export=download&id=1zj_iw_7T3M6BgmGZkFOIIGNghr02dWPk",
        "local_path": "C:\\Users\\Good PC\\Desktop\\AI基礎學習平台專案\\data\\cap_practice_sources\\109\\shared\\109_answers.pdf",
        "desktop_pdf_path": "C:\\Users\\Good PC\\Desktop\\國中題庫pdf\\會考歷屆練習\\109\\shared\\109_answers.pdf",
        "word_path": "C:\\Users\\Good PC\\Desktop\\AI基礎學習平台專案\\data\\cap_practice_word\\109\\shared\\109_answers.docx",
        "desktop_word_path": "C:\\Users\\Good PC\\Desktop\\國中題庫\\會考歷屆練習\\109\\shared\\109_answers.docx"
      },
      "explanation": {
        "label": "試題說明",
        "url": "https://drive.google.com/file/d/1QcMOuGHaby1_huKWY6a2gSt6Vm0GusW7/view?usp=drive_link",
        "download_url": "https://drive.google.com/uc?export=download&id=1QcMOuGHaby1_huKWY6a2gSt6Vm0GusW7",
        "local_path": "C:\\Users\\Good PC\\Desktop\\AI基礎學習平台專案\\data\\cap_practice_sources\\109\\shared\\109_explanation.pdf",
        "desktop_pdf_path": "C:\\Users\\Good PC\\Desktop\\國中題庫pdf\\會考歷屆練習\\109\\shared\\109_explanation.pdf",
        "word_path": "C:\\Users\\Good PC\\Desktop\\AI基礎學習平台專案\\data\\cap_practice_word\\109\\shared\\109_explanation.docx",
        "desktop_word_path": "C:\\Users\\Good PC\\Desktop\\國中題庫\\會考歷屆練習\\109\\shared\\109_explanation.docx"
      },
      "subjects": [
        {
          "slug": "chinese",
          "label": "國文",
          "question": {
            "label": "國文科",
            "url": "https://drive.google.com/file/d/1RpB4Y6I7FE2ADaTm-lKQYFLZU8LLjRhx/view?usp=drive_link",
            "download_url": "https://drive.google.com/uc?export=download&id=1RpB4Y6I7FE2ADaTm-lKQYFLZU8LLjRhx",
            "local_path": "C:\\Users\\Good PC\\Desktop\\AI基礎學習平台專案\\data\\cap_practice_sources\\109\\chinese\\109_chinese.pdf",
            "desktop_pdf_path": "C:\\Users\\Good PC\\Desktop\\國中題庫pdf\\會考歷屆練習\\109\\chinese\\109_chinese.pdf",
            "word_path": "C:\\Users\\Good PC\\Desktop\\AI基礎學習平台專案\\data\\cap_practice_word\\109\\chinese\\109_chinese.docx",
            "desktop_word_path": "C:\\Users\\Good PC\\Desktop\\國中題庫\\會考歷屆練習\\109\\chinese\\109_chinese.docx"
          }
        },
        {
          "slug": "english",
          "label": "英語",
          "question": {
            "label": "英語（閱讀）",
            "url": "https://drive.google.com/file/d/14uTgONqVcy8uRMe0rgRWr7CRBvkp5TJ1/view?usp=drive_link",
            "download_url": "https://drive.google.com/uc?export=download&id=14uTgONqVcy8uRMe0rgRWr7CRBvkp5TJ1",
            "local_path": "C:\\Users\\Good PC\\Desktop\\AI基礎學習平台專案\\data\\cap_practice_sources\\109\\english\\109_english.pdf",
            "desktop_pdf_path": "C:\\Users\\Good PC\\Desktop\\國中題庫pdf\\會考歷屆練習\\109\\english\\109_english.pdf",
            "word_path": "C:\\Users\\Good PC\\Desktop\\AI基礎學習平台專案\\data\\cap_practice_word\\109\\english\\109_english.docx",
            "desktop_word_path": "C:\\Users\\Good PC\\Desktop\\國中題庫\\會考歷屆練習\\109\\english\\109_english.docx"
          }
        },
        {
          "slug": "math",
          "label": "數學",
          "question": {
            "label": "數學科",
            "url": "https://drive.google.com/file/d/1jZJWQoO6mQZ_vWMmBcpJMC7bHdXIiJf0/view?usp=drive_link",
            "download_url": "https://drive.google.com/uc?export=download&id=1jZJWQoO6mQZ_vWMmBcpJMC7bHdXIiJf0",
            "local_path": "C:\\Users\\Good PC\\Desktop\\AI基礎學習平台專案\\data\\cap_practice_sources\\109\\math\\109_math.pdf",
            "desktop_pdf_path": "C:\\Users\\Good PC\\Desktop\\國中題庫pdf\\會考歷屆練習\\109\\math\\109_math.pdf",
            "word_path": "C:\\Users\\Good PC\\Desktop\\AI基礎學習平台專案\\data\\cap_practice_word\\109\\math\\109_math.docx",
            "desktop_word_path": "C:\\Users\\Good PC\\Desktop\\國中題庫\\會考歷屆練習\\109\\math\\109_math.docx"
          }
        },
        {
          "slug": "social",
          "label": "社會",
          "question": {
            "label": "社會科",
            "url": "https://drive.google.com/file/d/1y_1Sc8yH-iHtS6eBcLOCm_9fnmL2aFjf/view?usp=drive_link",
            "download_url": "https://drive.google.com/uc?export=download&id=1y_1Sc8yH-iHtS6eBcLOCm_9fnmL2aFjf",
            "local_path": "C:\\Users\\Good PC\\Desktop\\AI基礎學習平台專案\\data\\cap_practice_sources\\109\\social\\109_social.pdf",
            "desktop_pdf_path": "C:\\Users\\Good PC\\Desktop\\國中題庫pdf\\會考歷屆練習\\109\\social\\109_social.pdf",
            "word_path": "C:\\Users\\Good PC\\Desktop\\AI基礎學習平台專案\\data\\cap_practice_word\\109\\social\\109_social.docx",
            "desktop_word_path": "C:\\Users\\Good PC\\Desktop\\國中題庫\\會考歷屆練習\\109\\social\\109_social.docx"
          }
        },
        {
          "slug": "science",
          "label": "自然",
          "question": {
            "label": "自然科",
            "url": "https://drive.google.com/file/d/1nDVCh0u-MAApDFlv0kTVhFr_v7VKNVgP/view?usp=drive_link",
            "download_url": "https://drive.google.com/uc?export=download&id=1nDVCh0u-MAApDFlv0kTVhFr_v7VKNVgP",
            "local_path": "C:\\Users\\Good PC\\Desktop\\AI基礎學習平台專案\\data\\cap_practice_sources\\109\\science\\109_science.pdf",
            "desktop_pdf_path": "C:\\Users\\Good PC\\Desktop\\國中題庫pdf\\會考歷屆練習\\109\\science\\109_science.pdf",
            "word_path": "C:\\Users\\Good PC\\Desktop\\AI基礎學習平台專案\\data\\cap_practice_word\\109\\science\\109_science.docx",
            "desktop_word_path": "C:\\Users\\Good PC\\Desktop\\國中題庫\\會考歷屆練習\\109\\science\\109_science.docx"
          }
        }
      ],
      "issues": []
    },
    {
      "year": "110",
      "source_url": "https://cap.rcpet.edu.tw/exam/110/110exam.html",
      "answer": {
        "label": "參考答案",
        "url": "https://drive.google.com/file/d/1z7jBxC9t24e2Y3WK71XxWe0JOjJRLcNW/view?usp=drive_link",
        "download_url": "https://drive.google.com/uc?export=download&id=1z7jBxC9t24e2Y3WK71XxWe0JOjJRLcNW",
        "local_path": "C:\\Users\\Good PC\\Desktop\\AI基礎學習平台專案\\data\\cap_practice_sources\\110\\shared\\110_answers.pdf",
        "desktop_pdf_path": "C:\\Users\\Good PC\\Desktop\\國中題庫pdf\\會考歷屆練習\\110\\shared\\110_answers.pdf",
        "word_path": "C:\\Users\\Good PC\\Desktop\\AI基礎學習平台專案\\data\\cap_practice_word\\110\\shared\\110_answers.docx",
        "desktop_word_path": "C:\\Users\\Good PC\\Desktop\\國中題庫\\會考歷屆練習\\110\\shared\\110_answers.docx"
      },
      "explanation": {
        "label": "試題說明",
        "url": "https://drive.google.com/file/d/1TQg3cRXlQfSAAbH4keJGSGT1n4sFjwN5/view?usp=drive_link",
        "download_url": "https://drive.google.com/uc?export=download&id=1TQg3cRXlQfSAAbH4keJGSGT1n4sFjwN5",
        "local_path": "C:\\Users\\Good PC\\Desktop\\AI基礎學習平台專案\\data\\cap_practice_sources\\110\\shared\\110_explanation.pdf",
        "desktop_pdf_path": "C:\\Users\\Good PC\\Desktop\\國中題庫pdf\\會考歷屆練習\\110\\shared\\110_explanation.pdf",
        "word_path": "C:\\Users\\Good PC\\Desktop\\AI基礎學習平台專案\\data\\cap_practice_word\\110\\shared\\110_explanation.docx",
        "desktop_word_path": "C:\\Users\\Good PC\\Desktop\\國中題庫\\會考歷屆練習\\110\\shared\\110_explanation.docx"
      },
      "subjects": [
        {
          "slug": "chinese",
          "label": "國文",
          "question": {
            "label": "國文科",
            "url": "https://drive.google.com/file/d/1z5dk4Ar0QaZT_6dPsu2ZVP8_OBwe6LnS/view?usp=drive_link",
            "download_url": "https://drive.google.com/uc?export=download&id=1z5dk4Ar0QaZT_6dPsu2ZVP8_OBwe6LnS",
            "local_path": "C:\\Users\\Good PC\\Desktop\\AI基礎學習平台專案\\data\\cap_practice_sources\\110\\chinese\\110_chinese.pdf",
            "desktop_pdf_path": "C:\\Users\\Good PC\\Desktop\\國中題庫pdf\\會考歷屆練習\\110\\chinese\\110_chinese.pdf",
            "word_path": "C:\\Users\\Good PC\\Desktop\\AI基礎學習平台專案\\data\\cap_practice_word\\110\\chinese\\110_chinese.docx",
            "desktop_word_path": "C:\\Users\\Good PC\\Desktop\\國中題庫\\會考歷屆練習\\110\\chinese\\110_chinese.docx"
          }
        },
        {
          "slug": "english",
          "label": "英語",
          "question": {
            "label": "英語（閱讀）",
            "url": "https://drive.google.com/file/d/1jeGXKMm5auA68Z7SGzQo-bXq1opG6Knt/view?usp=drive_link",
            "download_url": "https://drive.google.com/uc?export=download&id=1jeGXKMm5auA68Z7SGzQo-bXq1opG6Knt",
            "local_path": "C:\\Users\\Good PC\\Desktop\\AI基礎學習平台專案\\data\\cap_practice_sources\\110\\english\\110_english.pdf",
            "desktop_pdf_path": "C:\\Users\\Good PC\\Desktop\\國中題庫pdf\\會考歷屆練習\\110\\english\\110_english.pdf",
            "word_path": "C:\\Users\\Good PC\\Desktop\\AI基礎學習平台專案\\data\\cap_practice_word\\110\\english\\110_english.docx",
            "desktop_word_path": "C:\\Users\\Good PC\\Desktop\\國中題庫\\會考歷屆練習\\110\\english\\110_english.docx"
          }
        },
        {
          "slug": "math",
          "label": "數學",
          "question": {
            "label": "數學科",
            "url": "https://drive.google.com/file/d/1sKc4iLzr8WlbbxMA83Y0NNryYv9rqHiG/view?usp=drive_link",
            "download_url": "https://drive.google.com/uc?export=download&id=1sKc4iLzr8WlbbxMA83Y0NNryYv9rqHiG",
            "local_path": "C:\\Users\\Good PC\\Desktop\\AI基礎學習平台專案\\data\\cap_practice_sources\\110\\math\\110_math.pdf",
            "desktop_pdf_path": "C:\\Users\\Good PC\\Desktop\\國中題庫pdf\\會考歷屆練習\\110\\math\\110_math.pdf",
            "word_path": "C:\\Users\\Good PC\\Desktop\\AI基礎學習平台專案\\data\\cap_practice_word\\110\\math\\110_math.docx",
            "desktop_word_path": "C:\\Users\\Good PC\\Desktop\\國中題庫\\會考歷屆練習\\110\\math\\110_math.docx"
          }
        },
        {
          "slug": "social",
          "label": "社會",
          "question": {
            "label": "社會科",
            "url": "https://drive.google.com/file/d/1pBrjHnXMCyTGmZgThvLVBpBlZaQkyU9t/view?usp=drive_link",
            "download_url": "https://drive.google.com/uc?export=download&id=1pBrjHnXMCyTGmZgThvLVBpBlZaQkyU9t",
            "local_path": "C:\\Users\\Good PC\\Desktop\\AI基礎學習平台專案\\data\\cap_practice_sources\\110\\social\\110_social.pdf",
            "desktop_pdf_path": "C:\\Users\\Good PC\\Desktop\\國中題庫pdf\\會考歷屆練習\\110\\social\\110_social.pdf",
            "word_path": "C:\\Users\\Good PC\\Desktop\\AI基礎學習平台專案\\data\\cap_practice_word\\110\\social\\110_social.docx",
            "desktop_word_path": "C:\\Users\\Good PC\\Desktop\\國中題庫\\會考歷屆練習\\110\\social\\110_social.docx"
          }
        },
        {
          "slug": "science",
          "label": "自然",
          "question": {
            "label": "自然科",
            "url": "https://drive.google.com/file/d/124Y-9HcPGeNzpQPe6Osl4X7A_xNIT0UA/view?usp=drive_link",
            "download_url": "https://drive.google.com/uc?export=download&id=124Y-9HcPGeNzpQPe6Osl4X7A_xNIT0UA",
            "local_path": "C:\\Users\\Good PC\\Desktop\\AI基礎學習平台專案\\data\\cap_practice_sources\\110\\science\\110_science.pdf",
            "desktop_pdf_path": "C:\\Users\\Good PC\\Desktop\\國中題庫pdf\\會考歷屆練習\\110\\science\\110_science.pdf",
            "word_path": "C:\\Users\\Good PC\\Desktop\\AI基礎學習平台專案\\data\\cap_practice_word\\110\\science\\110_science.docx",
            "desktop_word_path": "C:\\Users\\Good PC\\Desktop\\國中題庫\\會考歷屆練習\\110\\science\\110_science.docx"
          }
        }
      ],
      "issues": []
    },
    {
      "year": "111",
      "source_url": "https://cap.rcpet.edu.tw/exam/111/111exam.html",
      "answer": {
        "label": "參考答案",
        "url": "https://drive.google.com/file/d/1IeMHI4BmTpC_2Oc1lQ1Qj6XWHDf9qwGd/view?usp=drive_link",
        "download_url": "https://drive.google.com/uc?export=download&id=1IeMHI4BmTpC_2Oc1lQ1Qj6XWHDf9qwGd",
        "local_path": "C:\\Users\\Good PC\\Desktop\\AI基礎學習平台專案\\data\\cap_practice_sources\\111\\shared\\111_answers.pdf",
        "desktop_pdf_path": "C:\\Users\\Good PC\\Desktop\\國中題庫pdf\\會考歷屆練習\\111\\shared\\111_answers.pdf",
        "word_path": "C:\\Users\\Good PC\\Desktop\\AI基礎學習平台專案\\data\\cap_practice_word\\111\\shared\\111_answers.docx",
        "desktop_word_path": "C:\\Users\\Good PC\\Desktop\\國中題庫\\會考歷屆練習\\111\\shared\\111_answers.docx"
      },
      "explanation": {
        "label": "試題說明",
        "url": "https://drive.google.com/file/d/17TjMgVA4xXZYPlSPW9idgheMY9LR5agy/view?usp=drive_link",
        "download_url": "https://drive.google.com/uc?export=download&id=17TjMgVA4xXZYPlSPW9idgheMY9LR5agy",
        "local_path": "C:\\Users\\Good PC\\Desktop\\AI基礎學習平台專案\\data\\cap_practice_sources\\111\\shared\\111_explanation.pdf",
        "desktop_pdf_path": "C:\\Users\\Good PC\\Desktop\\國中題庫pdf\\會考歷屆練習\\111\\shared\\111_explanation.pdf",
        "word_path": "C:\\Users\\Good PC\\Desktop\\AI基礎學習平台專案\\data\\cap_practice_word\\111\\shared\\111_explanation.docx",
        "desktop_word_path": "C:\\Users\\Good PC\\Desktop\\國中題庫\\會考歷屆練習\\111\\shared\\111_explanation.docx"
      },
      "subjects": [
        {
          "slug": "chinese",
          "label": "國文",
          "question": {
            "label": "國文科",
            "url": "https://drive.google.com/file/d/174XqqVxF7_kIR7aqRaHpDe9m8-YJBFzY/view?usp=drive_link",
            "download_url": "https://drive.google.com/uc?export=download&id=174XqqVxF7_kIR7aqRaHpDe9m8-YJBFzY",
            "local_path": "C:\\Users\\Good PC\\Desktop\\AI基礎學習平台專案\\data\\cap_practice_sources\\111\\chinese\\111_chinese.pdf",
            "desktop_pdf_path": "C:\\Users\\Good PC\\Desktop\\國中題庫pdf\\會考歷屆練習\\111\\chinese\\111_chinese.pdf",
            "word_path": "C:\\Users\\Good PC\\Desktop\\AI基礎學習平台專案\\data\\cap_practice_word\\111\\chinese\\111_chinese.docx",
            "desktop_word_path": "C:\\Users\\Good PC\\Desktop\\國中題庫\\會考歷屆練習\\111\\chinese\\111_chinese.docx"
          }
        },
        {
          "slug": "english",
          "label": "英語",
          "question": {
            "label": "英語（閱讀）",
            "url": "https://drive.google.com/file/d/1IyJBtIjySeyVAisE1YiCclYsSldQpHBf/view?usp=drive_link",
            "download_url": "https://drive.google.com/uc?export=download&id=1IyJBtIjySeyVAisE1YiCclYsSldQpHBf",
            "local_path": "C:\\Users\\Good PC\\Desktop\\AI基礎學習平台專案\\data\\cap_practice_sources\\111\\english\\111_english.pdf",
            "desktop_pdf_path": "C:\\Users\\Good PC\\Desktop\\國中題庫pdf\\會考歷屆練習\\111\\english\\111_english.pdf",
            "word_path": "C:\\Users\\Good PC\\Desktop\\AI基礎學習平台專案\\data\\cap_practice_word\\111\\english\\111_english.docx",
            "desktop_word_path": "C:\\Users\\Good PC\\Desktop\\國中題庫\\會考歷屆練習\\111\\english\\111_english.docx"
          }
        },
        {
          "slug": "math",
          "label": "數學",
          "question": {
            "label": "數學科",
            "url": "https://drive.google.com/file/d/15GDoX37pXdUsluIw79o2bkhgfiL1HxCG/view?usp=drive_link",
            "download_url": "https://drive.google.com/uc?export=download&id=15GDoX37pXdUsluIw79o2bkhgfiL1HxCG",
            "local_path": "C:\\Users\\Good PC\\Desktop\\AI基礎學習平台專案\\data\\cap_practice_sources\\111\\math\\111_math.pdf",
            "desktop_pdf_path": "C:\\Users\\Good PC\\Desktop\\國中題庫pdf\\會考歷屆練習\\111\\math\\111_math.pdf",
            "word_path": "C:\\Users\\Good PC\\Desktop\\AI基礎學習平台專案\\data\\cap_practice_word\\111\\math\\111_math.docx",
            "desktop_word_path": "C:\\Users\\Good PC\\Desktop\\國中題庫\\會考歷屆練習\\111\\math\\111_math.docx"
          }
        },
        {
          "slug": "social",
          "label": "社會",
          "question": {
            "label": "社會科",
            "url": "https://drive.google.com/file/d/1th-vb5HCBAhIv65OKXY646kHYbyggwQu/view?usp=drive_link",
            "download_url": "https://drive.google.com/uc?export=download&id=1th-vb5HCBAhIv65OKXY646kHYbyggwQu",
            "local_path": "C:\\Users\\Good PC\\Desktop\\AI基礎學習平台專案\\data\\cap_practice_sources\\111\\social\\111_social.pdf",
            "desktop_pdf_path": "C:\\Users\\Good PC\\Desktop\\國中題庫pdf\\會考歷屆練習\\111\\social\\111_social.pdf",
            "word_path": "C:\\Users\\Good PC\\Desktop\\AI基礎學習平台專案\\data\\cap_practice_word\\111\\social\\111_social.docx",
            "desktop_word_path": "C:\\Users\\Good PC\\Desktop\\國中題庫\\會考歷屆練習\\111\\social\\111_social.docx"
          }
        },
        {
          "slug": "science",
          "label": "自然",
          "question": {
            "label": "自然科",
            "url": "https://drive.google.com/file/d/1OiQVdqtDQauNW_qwlCFTWLmcfBHuCjdm/view?usp=drive_link",
            "download_url": "https://drive.google.com/uc?export=download&id=1OiQVdqtDQauNW_qwlCFTWLmcfBHuCjdm",
            "local_path": "C:\\Users\\Good PC\\Desktop\\AI基礎學習平台專案\\data\\cap_practice_sources\\111\\science\\111_science.pdf",
            "desktop_pdf_path": "C:\\Users\\Good PC\\Desktop\\國中題庫pdf\\會考歷屆練習\\111\\science\\111_science.pdf",
            "word_path": "C:\\Users\\Good PC\\Desktop\\AI基礎學習平台專案\\data\\cap_practice_word\\111\\science\\111_science.docx",
            "desktop_word_path": "C:\\Users\\Good PC\\Desktop\\國中題庫\\會考歷屆練習\\111\\science\\111_science.docx"
          }
        }
      ],
      "issues": []
    },
    {
      "year": "112",
      "source_url": "https://cap.rcpet.edu.tw/exam/112/112exam.html",
      "answer": {
        "label": "參考答案",
        "url": "https://drive.google.com/file/d/1OT5r0que_0bXSy0kwLEOEJMssce2OnL0/view?usp=drive_link",
        "download_url": "https://drive.google.com/uc?export=download&id=1OT5r0que_0bXSy0kwLEOEJMssce2OnL0",
        "local_path": "C:\\Users\\Good PC\\Desktop\\AI基礎學習平台專案\\data\\cap_practice_sources\\112\\shared\\112_answers.pdf",
        "desktop_pdf_path": "C:\\Users\\Good PC\\Desktop\\國中題庫pdf\\會考歷屆練習\\112\\shared\\112_answers.pdf",
        "word_path": "C:\\Users\\Good PC\\Desktop\\AI基礎學習平台專案\\data\\cap_practice_word\\112\\shared\\112_answers.docx",
        "desktop_word_path": "C:\\Users\\Good PC\\Desktop\\國中題庫\\會考歷屆練習\\112\\shared\\112_answers.docx"
      },
      "explanation": {
        "label": "試題說明",
        "url": "https://drive.google.com/file/d/1ryCrnCTkwWib6PTbw-PPHCcV7K3Tc2p4/view?usp=drive_link",
        "download_url": "https://drive.google.com/uc?export=download&id=1ryCrnCTkwWib6PTbw-PPHCcV7K3Tc2p4",
        "local_path": "C:\\Users\\Good PC\\Desktop\\AI基礎學習平台專案\\data\\cap_practice_sources\\112\\shared\\112_explanation.pdf",
        "desktop_pdf_path": "C:\\Users\\Good PC\\Desktop\\國中題庫pdf\\會考歷屆練習\\112\\shared\\112_explanation.pdf",
        "word_path": "C:\\Users\\Good PC\\Desktop\\AI基礎學習平台專案\\data\\cap_practice_word\\112\\shared\\112_explanation.docx",
        "desktop_word_path": "C:\\Users\\Good PC\\Desktop\\國中題庫\\會考歷屆練習\\112\\shared\\112_explanation.docx"
      },
      "subjects": [
        {
          "slug": "chinese",
          "label": "國文",
          "question": {
            "label": "國文科",
            "url": "https://drive.google.com/file/d/1dy9SuFFJro5R8SOIZRbA8ytq2Ol-UnZ9/view?usp=drive_link",
            "download_url": "https://drive.google.com/uc?export=download&id=1dy9SuFFJro5R8SOIZRbA8ytq2Ol-UnZ9",
            "local_path": "C:\\Users\\Good PC\\Desktop\\AI基礎學習平台專案\\data\\cap_practice_sources\\112\\chinese\\112_chinese.pdf",
            "desktop_pdf_path": "C:\\Users\\Good PC\\Desktop\\國中題庫pdf\\會考歷屆練習\\112\\chinese\\112_chinese.pdf",
            "word_path": "C:\\Users\\Good PC\\Desktop\\AI基礎學習平台專案\\data\\cap_practice_word\\112\\chinese\\112_chinese.docx",
            "desktop_word_path": "C:\\Users\\Good PC\\Desktop\\國中題庫\\會考歷屆練習\\112\\chinese\\112_chinese.docx"
          }
        },
        {
          "slug": "english",
          "label": "英語",
          "question": {
            "label": "英語（閱讀）",
            "url": "https://drive.google.com/file/d/1SXbjT6B_F8eQh2GZEvB6KmgR0k2lDK8A/view?usp=drive_link",
            "download_url": "https://drive.google.com/uc?export=download&id=1SXbjT6B_F8eQh2GZEvB6KmgR0k2lDK8A",
            "local_path": "C:\\Users\\Good PC\\Desktop\\AI基礎學習平台專案\\data\\cap_practice_sources\\112\\english\\112_english.pdf",
            "desktop_pdf_path": "C:\\Users\\Good PC\\Desktop\\國中題庫pdf\\會考歷屆練習\\112\\english\\112_english.pdf",
            "word_path": "C:\\Users\\Good PC\\Desktop\\AI基礎學習平台專案\\data\\cap_practice_word\\112\\english\\112_english.docx",
            "desktop_word_path": "C:\\Users\\Good PC\\Desktop\\國中題庫\\會考歷屆練習\\112\\english\\112_english.docx"
          }
        },
        {
          "slug": "math",
          "label": "數學",
          "question": {
            "label": "數學科",
            "url": "https://drive.google.com/file/d/1im3JF0E8d8RC__Z8MW9MQXCuonjPN3f_/view?usp=drive_link",
            "download_url": "https://drive.google.com/uc?export=download&id=1im3JF0E8d8RC__Z8MW9MQXCuonjPN3f_",
            "local_path": "C:\\Users\\Good PC\\Desktop\\AI基礎學習平台專案\\data\\cap_practice_sources\\112\\math\\112_math.pdf",
            "desktop_pdf_path": "C:\\Users\\Good PC\\Desktop\\國中題庫pdf\\會考歷屆練習\\112\\math\\112_math.pdf",
            "word_path": "C:\\Users\\Good PC\\Desktop\\AI基礎學習平台專案\\data\\cap_practice_word\\112\\math\\112_math.docx",
            "desktop_word_path": "C:\\Users\\Good PC\\Desktop\\國中題庫\\會考歷屆練習\\112\\math\\112_math.docx"
          }
        },
        {
          "slug": "social",
          "label": "社會",
          "question": {
            "label": "社會科",
            "url": "https://drive.google.com/file/d/1vIVX90btDzk3XnNVfSQv0wRTw2A6omjL/view?usp=drive_link",
            "download_url": "https://drive.google.com/uc?export=download&id=1vIVX90btDzk3XnNVfSQv0wRTw2A6omjL",
            "local_path": "C:\\Users\\Good PC\\Desktop\\AI基礎學習平台專案\\data\\cap_practice_sources\\112\\social\\112_social.pdf",
            "desktop_pdf_path": "C:\\Users\\Good PC\\Desktop\\國中題庫pdf\\會考歷屆練習\\112\\social\\112_social.pdf",
            "word_path": "C:\\Users\\Good PC\\Desktop\\AI基礎學習平台專案\\data\\cap_practice_word\\112\\social\\112_social.docx",
            "desktop_word_path": "C:\\Users\\Good PC\\Desktop\\國中題庫\\會考歷屆練習\\112\\social\\112_social.docx"
          }
        },
        {
          "slug": "science",
          "label": "自然",
          "question": {
            "label": "自然科",
            "url": "https://drive.google.com/file/d/1Bo87vJFakmGzyUqqjHzTCF-fv75DFgx_/view?usp=drive_link",
            "download_url": "https://drive.google.com/uc?export=download&id=1Bo87vJFakmGzyUqqjHzTCF-fv75DFgx_",
            "local_path": "C:\\Users\\Good PC\\Desktop\\AI基礎學習平台專案\\data\\cap_practice_sources\\112\\science\\112_science.pdf",
            "desktop_pdf_path": "C:\\Users\\Good PC\\Desktop\\國中題庫pdf\\會考歷屆練習\\112\\science\\112_science.pdf",
            "word_path": "C:\\Users\\Good PC\\Desktop\\AI基礎學習平台專案\\data\\cap_practice_word\\112\\science\\112_science.docx",
            "desktop_word_path": "C:\\Users\\Good PC\\Desktop\\國中題庫\\會考歷屆練習\\112\\science\\112_science.docx"
          }
        }
      ],
      "issues": []
    },
    {
      "year": "113",
      "source_url": "https://cap.rcpet.edu.tw/exam/113/113exam.html",
      "answer": {
        "label": "參考答案",
        "url": "https://drive.google.com/file/d/1cWlogP9FBRX1eD5kjgVDP2_6f8VCLSB4/view?usp=drive_link",
        "download_url": "https://drive.google.com/uc?export=download&id=1cWlogP9FBRX1eD5kjgVDP2_6f8VCLSB4",
        "local_path": "C:\\Users\\Good PC\\Desktop\\AI基礎學習平台專案\\data\\cap_practice_sources\\113\\shared\\113_answers.pdf",
        "desktop_pdf_path": "C:\\Users\\Good PC\\Desktop\\國中題庫pdf\\會考歷屆練習\\113\\shared\\113_answers.pdf",
        "word_path": "C:\\Users\\Good PC\\Desktop\\AI基礎學習平台專案\\data\\cap_practice_word\\113\\shared\\113_answers.docx",
        "desktop_word_path": "C:\\Users\\Good PC\\Desktop\\國中題庫\\會考歷屆練習\\113\\shared\\113_answers.docx"
      },
      "explanation": {
        "label": "試題說明",
        "url": "https://drive.google.com/file/d/1YzrMP9JN6st0fcL5Vg_D0J75wUSBHOpW/view?usp=drive_link",
        "download_url": "https://drive.google.com/uc?export=download&id=1YzrMP9JN6st0fcL5Vg_D0J75wUSBHOpW",
        "local_path": "C:\\Users\\Good PC\\Desktop\\AI基礎學習平台專案\\data\\cap_practice_sources\\113\\shared\\113_explanation.pdf",
        "desktop_pdf_path": "C:\\Users\\Good PC\\Desktop\\國中題庫pdf\\會考歷屆練習\\113\\shared\\113_explanation.pdf",
        "word_path": "C:\\Users\\Good PC\\Desktop\\AI基礎學習平台專案\\data\\cap_practice_word\\113\\shared\\113_explanation.docx",
        "desktop_word_path": "C:\\Users\\Good PC\\Desktop\\國中題庫\\會考歷屆練習\\113\\shared\\113_explanation.docx"
      },
      "subjects": [
        {
          "slug": "chinese",
          "label": "國文",
          "question": {
            "label": "國文科",
            "url": "https://drive.google.com/file/d/1Xr5AwMNQipYZblCEbZadyBvLVcT_8XSv/view?usp=drive_link",
            "download_url": "https://drive.google.com/uc?export=download&id=1Xr5AwMNQipYZblCEbZadyBvLVcT_8XSv",
            "local_path": "C:\\Users\\Good PC\\Desktop\\AI基礎學習平台專案\\data\\cap_practice_sources\\113\\chinese\\113_chinese.pdf",
            "desktop_pdf_path": "C:\\Users\\Good PC\\Desktop\\國中題庫pdf\\會考歷屆練習\\113\\chinese\\113_chinese.pdf",
            "word_path": "C:\\Users\\Good PC\\Desktop\\AI基礎學習平台專案\\data\\cap_practice_word\\113\\chinese\\113_chinese.docx",
            "desktop_word_path": "C:\\Users\\Good PC\\Desktop\\國中題庫\\會考歷屆練習\\113\\chinese\\113_chinese.docx"
          }
        },
        {
          "slug": "english",
          "label": "英語",
          "question": {
            "label": "英語（閱讀）",
            "url": "https://drive.google.com/file/d/1ZU8SG-4jdV1DGvPzpgzoi_hhRiD4NT3S/view?usp=drive_link",
            "download_url": "https://drive.google.com/uc?export=download&id=1ZU8SG-4jdV1DGvPzpgzoi_hhRiD4NT3S",
            "local_path": "C:\\Users\\Good PC\\Desktop\\AI基礎學習平台專案\\data\\cap_practice_sources\\113\\english\\113_english.pdf",
            "desktop_pdf_path": "C:\\Users\\Good PC\\Desktop\\國中題庫pdf\\會考歷屆練習\\113\\english\\113_english.pdf",
            "word_path": "C:\\Users\\Good PC\\Desktop\\AI基礎學習平台專案\\data\\cap_practice_word\\113\\english\\113_english.docx",
            "desktop_word_path": "C:\\Users\\Good PC\\Desktop\\國中題庫\\會考歷屆練習\\113\\english\\113_english.docx"
          }
        },
        {
          "slug": "math",
          "label": "數學",
          "question": {
            "label": "數學科",
            "url": "https://drive.google.com/file/d/1MXfrOI_4KyxF6A-2NNd_J_eIuo3Epa46/view?usp=drive_link",
            "download_url": "https://drive.google.com/uc?export=download&id=1MXfrOI_4KyxF6A-2NNd_J_eIuo3Epa46",
            "local_path": "C:\\Users\\Good PC\\Desktop\\AI基礎學習平台專案\\data\\cap_practice_sources\\113\\math\\113_math.pdf",
            "desktop_pdf_path": "C:\\Users\\Good PC\\Desktop\\國中題庫pdf\\會考歷屆練習\\113\\math\\113_math.pdf",
            "word_path": "C:\\Users\\Good PC\\Desktop\\AI基礎學習平台專案\\data\\cap_practice_word\\113\\math\\113_math.docx",
            "desktop_word_path": "C:\\Users\\Good PC\\Desktop\\國中題庫\\會考歷屆練習\\113\\math\\113_math.docx"
          }
        },
        {
          "slug": "social",
          "label": "社會",
          "question": {
            "label": "社會科",
            "url": "https://drive.google.com/file/d/1NJYibw-N2mHZP5lL8-rOhirWv_ZFQNiz/view?usp=drive_link",
            "download_url": "https://drive.google.com/uc?export=download&id=1NJYibw-N2mHZP5lL8-rOhirWv_ZFQNiz",
            "local_path": "C:\\Users\\Good PC\\Desktop\\AI基礎學習平台專案\\data\\cap_practice_sources\\113\\social\\113_social.pdf",
            "desktop_pdf_path": "C:\\Users\\Good PC\\Desktop\\國中題庫pdf\\會考歷屆練習\\113\\social\\113_social.pdf",
            "word_path": "C:\\Users\\Good PC\\Desktop\\AI基礎學習平台專案\\data\\cap_practice_word\\113\\social\\113_social.docx",
            "desktop_word_path": "C:\\Users\\Good PC\\Desktop\\國中題庫\\會考歷屆練習\\113\\social\\113_social.docx"
          }
        },
        {
          "slug": "science",
          "label": "自然",
          "question": {
            "label": "自然科",
            "url": "https://drive.google.com/file/d/1lO1_3Iq62BmTHR8m29or7I8VtS8qZdDR/view?usp=drive_link",
            "download_url": "https://drive.google.com/uc?export=download&id=1lO1_3Iq62BmTHR8m29or7I8VtS8qZdDR",
            "local_path": "C:\\Users\\Good PC\\Desktop\\AI基礎學習平台專案\\data\\cap_practice_sources\\113\\science\\113_science.pdf",
            "desktop_pdf_path": "C:\\Users\\Good PC\\Desktop\\國中題庫pdf\\會考歷屆練習\\113\\science\\113_science.pdf",
            "word_path": "C:\\Users\\Good PC\\Desktop\\AI基礎學習平台專案\\data\\cap_practice_word\\113\\science\\113_science.docx",
            "desktop_word_path": "C:\\Users\\Good PC\\Desktop\\國中題庫\\會考歷屆練習\\113\\science\\113_science.docx"
          }
        }
      ],
      "issues": []
    },
    {
      "year": "114",
      "source_url": "https://cap.rcpet.edu.tw/exam/114/114exam.html",
      "answer": {
        "label": "參考答案",
        "url": "https://drive.google.com/file/d/175hz0lHG4GTDNxYet9lrRDu0lmC_G08o/view?usp=drive_link",
        "download_url": "https://drive.google.com/uc?export=download&id=175hz0lHG4GTDNxYet9lrRDu0lmC_G08o",
        "local_path": "C:\\Users\\Good PC\\Desktop\\AI基礎學習平台專案\\data\\cap_practice_sources\\114\\shared\\114_answers.pdf",
        "desktop_pdf_path": "C:\\Users\\Good PC\\Desktop\\國中題庫pdf\\會考歷屆練習\\114\\shared\\114_answers.pdf",
        "word_path": "C:\\Users\\Good PC\\Desktop\\AI基礎學習平台專案\\data\\cap_practice_word\\114\\shared\\114_answers.docx",
        "desktop_word_path": "C:\\Users\\Good PC\\Desktop\\國中題庫\\會考歷屆練習\\114\\shared\\114_answers.docx"
      },
      "explanation": {
        "label": "試題說明",
        "url": "https://drive.google.com/file/d/11HW_piDqYm9Gq6qo-BSONsxZ-jgTri4h/view?usp=drive_link",
        "download_url": "https://drive.google.com/uc?export=download&id=11HW_piDqYm9Gq6qo-BSONsxZ-jgTri4h",
        "local_path": "C:\\Users\\Good PC\\Desktop\\AI基礎學習平台專案\\data\\cap_practice_sources\\114\\shared\\114_explanation.pdf",
        "desktop_pdf_path": "C:\\Users\\Good PC\\Desktop\\國中題庫pdf\\會考歷屆練習\\114\\shared\\114_explanation.pdf",
        "word_path": "C:\\Users\\Good PC\\Desktop\\AI基礎學習平台專案\\data\\cap_practice_word\\114\\shared\\114_explanation.docx",
        "desktop_word_path": "C:\\Users\\Good PC\\Desktop\\國中題庫\\會考歷屆練習\\114\\shared\\114_explanation.docx"
      },
      "subjects": [
        {
          "slug": "chinese",
          "label": "國文",
          "question": {
            "label": "國文科",
            "url": "https://drive.google.com/file/d/102j8F3hoCvGgMCVP6x6oHN9cCd0R6_Ii/view?usp=drive_link",
            "download_url": "https://drive.google.com/uc?export=download&id=102j8F3hoCvGgMCVP6x6oHN9cCd0R6_Ii",
            "local_path": "C:\\Users\\Good PC\\Desktop\\AI基礎學習平台專案\\data\\cap_practice_sources\\114\\chinese\\114_chinese.pdf",
            "desktop_pdf_path": "C:\\Users\\Good PC\\Desktop\\國中題庫pdf\\會考歷屆練習\\114\\chinese\\114_chinese.pdf",
            "word_path": "C:\\Users\\Good PC\\Desktop\\AI基礎學習平台專案\\data\\cap_practice_word\\114\\chinese\\114_chinese.docx",
            "desktop_word_path": "C:\\Users\\Good PC\\Desktop\\國中題庫\\會考歷屆練習\\114\\chinese\\114_chinese.docx"
          }
        },
        {
          "slug": "english",
          "label": "英語",
          "question": {
            "label": "英語（閱讀）",
            "url": "https://drive.google.com/file/d/1Or0bC16Jn2hA0uAF2zrryHoY46ywIQjK/view?usp=drive_link",
            "download_url": "https://drive.google.com/uc?export=download&id=1Or0bC16Jn2hA0uAF2zrryHoY46ywIQjK",
            "local_path": "C:\\Users\\Good PC\\Desktop\\AI基礎學習平台專案\\data\\cap_practice_sources\\114\\english\\114_english.pdf",
            "desktop_pdf_path": "C:\\Users\\Good PC\\Desktop\\國中題庫pdf\\會考歷屆練習\\114\\english\\114_english.pdf",
            "word_path": "C:\\Users\\Good PC\\Desktop\\AI基礎學習平台專案\\data\\cap_practice_word\\114\\english\\114_english.docx",
            "desktop_word_path": "C:\\Users\\Good PC\\Desktop\\國中題庫\\會考歷屆練習\\114\\english\\114_english.docx"
          }
        },
        {
          "slug": "math",
          "label": "數學",
          "question": {
            "label": "數學科",
            "url": "https://drive.google.com/file/d/1c2AGC67Bq344EdGSZkO9SZhrY50hHTJx/view?usp=drive_link",
            "download_url": "https://drive.google.com/uc?export=download&id=1c2AGC67Bq344EdGSZkO9SZhrY50hHTJx",
            "local_path": "C:\\Users\\Good PC\\Desktop\\AI基礎學習平台專案\\data\\cap_practice_sources\\114\\math\\114_math.pdf",
            "desktop_pdf_path": "C:\\Users\\Good PC\\Desktop\\國中題庫pdf\\會考歷屆練習\\114\\math\\114_math.pdf",
            "word_path": "C:\\Users\\Good PC\\Desktop\\AI基礎學習平台專案\\data\\cap_practice_word\\114\\math\\114_math.docx",
            "desktop_word_path": "C:\\Users\\Good PC\\Desktop\\國中題庫\\會考歷屆練習\\114\\math\\114_math.docx"
          }
        },
        {
          "slug": "social",
          "label": "社會",
          "question": {
            "label": "社會科",
            "url": "https://drive.google.com/file/d/1vFl3qctoBXYcCtWbAqKUqhekIMgV6q-m/view?usp=drive_link",
            "download_url": "https://drive.google.com/uc?export=download&id=1vFl3qctoBXYcCtWbAqKUqhekIMgV6q-m",
            "local_path": "C:\\Users\\Good PC\\Desktop\\AI基礎學習平台專案\\data\\cap_practice_sources\\114\\social\\114_social.pdf",
            "desktop_pdf_path": "C:\\Users\\Good PC\\Desktop\\國中題庫pdf\\會考歷屆練習\\114\\social\\114_social.pdf",
            "word_path": "C:\\Users\\Good PC\\Desktop\\AI基礎學習平台專案\\data\\cap_practice_word\\114\\social\\114_social.docx",
            "desktop_word_path": "C:\\Users\\Good PC\\Desktop\\國中題庫\\會考歷屆練習\\114\\social\\114_social.docx"
          }
        },
        {
          "slug": "science",
          "label": "自然",
          "question": {
            "label": "自然科",
            "url": "https://drive.google.com/file/d/18_lHom7zYhyOoMvxHt4hKJS_CynFOoZ1/view?usp=drive_link",
            "download_url": "https://drive.google.com/uc?export=download&id=18_lHom7zYhyOoMvxHt4hKJS_CynFOoZ1",
            "local_path": "C:\\Users\\Good PC\\Desktop\\AI基礎學習平台專案\\data\\cap_practice_sources\\114\\science\\114_science.pdf",
            "desktop_pdf_path": "C:\\Users\\Good PC\\Desktop\\國中題庫pdf\\會考歷屆練習\\114\\science\\114_science.pdf",
            "word_path": "C:\\Users\\Good PC\\Desktop\\AI基礎學習平台專案\\data\\cap_practice_word\\114\\science\\114_science.docx",
            "desktop_word_path": "C:\\Users\\Good PC\\Desktop\\國中題庫\\會考歷屆練習\\114\\science\\114_science.docx"
          }
        }
      ],
      "issues": []
    }
  ]
}